{"cached_at": "2026-02-08T03:21:13.720148+00:00", "request": {"lat": 39.7684, "lng": -86.33391151197426, "radius": 5000}, "response": [{"id": "ChIJV4BWk1mvbIgRx_WbCa2yCno", "nationalPhoneNumber": "(317) 273-8966", "formattedAddress": "9682 E US Hwy 36, Avon, IN 46123, USA", "addressComponents": [{"longText": "9682", "shortText": "9682", "types": ["street_number"], "languageCode": "en-US"}, {"longText": "East US Highway 36", "shortText": "E US Hwy 36", "types": ["route"], "languageCode": "en"}, {"longText": "Avon", "shortText": "Avon", "types": ["locality", "political"], "languageCode": "en"}, {"longText": "Washington Township", "shortText": "Washington Township", "types": ["administrative_area_level_3", "political"], "languageCode": "en"}, {"longText": "Hendricks County", "shortText": "Hendricks County", "types": ["administrative_area_level_2", "political"], "languageCode": "en"}, {"longText": "Indiana", "shortText": "IN", "types": ["administrative_area_level_1", "political"], "languageCode": "en"}, {"longText": "United States", "shortText": "US", "types": ["country", "political"], "languageCode": "en"}, {"longText": "46123", "shortText": "46123", "types": ["postal_code"], "languageCode": "en-US"}], "location": {"latitude": 39.764066899999996, "longitude": -86.35170459999999}, "rating": 4.1, "googleMapsUri": "https://maps.google.com/?cid=8794037678654617031&g_mp=Cilnb29nbGUubWFwcy5wbGFjZXMudjEuUGxhY2VzLlNlYXJjaE5lYXJieRACGAQgAA", "websiteUri": "https://www.pandaexpress.com/locations/in/avon/1469", "regularOpeningHours": {"openNow": true, "periods": [{"open": {"day": 0, "hour": 10, "minute": 0}, "close": {"day": 0, "hour": 22, "minute": 30}}, {"open": {"day": 1, "hour": 10, "minute": 0}, "close": {"day": 1, "hour": 22, "minute": 30}}, {"open": {"day": 2, "hour": 10, "minute": 0}, "close": {"day": 2, "hour": 22, "minute": 30}}, {"open": {"day": 3, "hour": 10, "minute": 0}, "close": {"day": 3, "hour": 22, "minute": 30}}, {"open": {"day": 4, "hour": 10, "minute": 0}, "close": {"day": 4, "hour": 22, "minute": 30}}, {"open": {"day": 5, "hour": 10, "minute": 0}, "close": {"day": 5, "hour": 23, "minute": 0}}, {"open": {"day": 6, "hour": 10, "minute": 0}, "close": {"day": 6, "hour": 23, "minute": 0}}], "weekdayDescriptions": ["Monday: 10:00\u202fAM\u2009\u2013\u200910:30\u202fPM", "Tuesday: 10:00\u202fAM\u2009\u2013\u200910:30\u202fPM", "Wednesday: 10:00\u202fAM\u2009\u2013\u200910:30\u202fPM", "Thursday: 10:00\u202fAM\u2009\u2013\u200910:30\u202fPM", "Friday: 10:00\u202fAM\u2009\u2013\u200911:00\u202fPM", "Saturday: 10:00\u202fAM\u2009\u2013\u200911:00\u202fPM", "Sunday: 10:00\u202fAM\u2009\u2013\u200910:30\u202fPM"], "nextCloseTime": "2026-02-08T04:00:00Z"}, "businessStatus": "OPERATIONAL", "priceLevel": "PRICE_LEVEL_INEXPENSIVE", "userRatingCount": 1071, "displayName": {"text": "Panda Express", "languageCode": "en"}, "takeout": true, "delivery": true, "dineIn": true}, {"id": "ChIJNZU-MYGvbIgRDmeq6gsrk8c", "nationalPhoneNumber": "(317) 272-2888", "formattedAddress": "7736 E US Hwy 36, Avon, IN 46123, USA", "addressComponents": [{"longText": "7736", "shortText": "7736", "types": ["street_number"], "languageCode": "en-US"}, {"longText": "East US Highway 36", "shortText": "E US Hwy 36", "types": ["route"], "languageCode": "en"}, {"longText": "Avon", "shortText": "Avon", "types": ["locality", "political"], "languageCode": "en"}, {"longText": "Washington Township", "shortText": "Washington Township", "types": ["administrative_area_level_3", "political"], "languageCode": "en"}, {"longText": "Hendricks County", "shortText": "Hendricks County", "types": ["administrative_area_level_2", "political"], "languageCode": "en"}, {"longText": "Indiana", "shortText": "IN", "types": ["administrative_area_level_1", "political"], "languageCode": "en"}, {"longText": "United States", "shortText": "US", "types": ["country", "political"], "languageCode": "en"}, {"longText": "46123", "shortText": "46123", "types": ["postal_code"], "languageCode": "en-US"}], "location": {"latitude": 39.763495899999995, "longitude": -86.3859961}, "rating": 4, "googleMapsUri": "https://maps.google.com/?cid=14380885365305796366&g_mp=Cilnb29nbGUubWFwcy5wbGFjZXMudjEuUGxhY2VzLlNlYXJjaE5lYXJieRACGAQgAA", "websiteUri": "https://www.greatwallavon.com/", "regularOpeningHours": {"openNow": true, "periods": [{"open": {"day": 0, "hour": 11, "minute": 30}, "close": {"day": 0, "hour": 21, "minute": 30}}, {"open": {"day": 1, "hour": 10, "minute": 30}, "close": {"day": 1, "hour": 21, "minute": 30}}, {"open": {"day": 2, "hour": 10, "minute": 30}, "close": {"day": 2, "hour": 21, "minute": 30}}, {"open": {"day": 3, "hour": 10, "minute": 30}, "close": {"day": 3, "hour": 21, "minute": 30}}, {"open": {"day": 4, "hour": 10, "minute": 30}, "close": {"day": 4, "hour": 21, "minute": 30}}, {"open": {"day": 5, "hour": 10, "minute": 30}, "close": {"day": 5, "hour": 22, "minute": 30}}, {"open": {"day": 6, "hour": 10, "minute": 30}, "close": {"day": 6, "hour": 22, "minute": 30}}], "weekdayDescriptions": ["Monday: 10:30\u202fAM\u2009\u2013\u20099:30\u202fPM", "Tuesday: 10:30\u202fAM\u2009\u2013\u20099:30\u202fPM", "Wednesday: 10:30\u202fAM\u2009\u2013\u20099:30\u202fPM", "Thursday: 10:30\u202fAM\u2009\u2013\u20099:30\u202fPM", "Friday: 10:30\u202fAM\u2009\u2013\u200910:30\u202fPM", "Saturday: 10:30\u202fAM\u2009\u2013\u200910:30\u202fPM", "Sunday: 11:30\u202fAM\u2009\u2013\u20099:30\u202fPM"], "nextCloseTime": "2026-02-08T03:30:00Z"}, "businessStatus": "OPERATIONAL", "priceLevel": "PRICE_LEVEL_INEXPENSIVE", "userRatingCount": 258, "displayName": {"text": "Great Wall", "languageCode": "en"}, "takeout": true, "delivery": true, "dineIn": true}, {"id": "ChIJzT3MCV6obIgRqWjeTIoo4s4", "nationalPhoneNumber": "(317) 273-8899", "formattedAddress": "7451 W 10th St, Indianapolis, IN 46214, USA", "addressComponents": [{"longText": "7451", "shortText": "7451", "types": ["street_number"], "languageCode": "en-US"}, {"longText": "West 10th Street", "shortText": "W 10th St", "types": ["route"], "languageCode": "en"}, {"longText": "Chapel Hill / Ben Davis", "shortText": "Chapel Hill / Ben Davis", "types": ["neighborhood", "political"], "languageCode": "en"}, {"longText": "Indianapolis", "shortText": "Indianapolis", "types": ["locality", "political"], "languageCode": "en"}, {"longText": "Wayne Township", "shortText": "Wayne Township", "types": ["administrative_area_level_3", "political"], "languageCode": "en"}, {"longText": "Marion County", "shortText": "Marion County", "types": ["administrative_area_level_2", "political"], "languageCode": "en"}, {"longText": "Indiana", "shortText": "IN", "types": ["administrative_area_level_1", "political"], "languageCode": "en"}, {"longText": "United States", "shortText": "US", "types": ["country", "political"], "languageCode": "en"}, {"longText": "46214", "shortText": "46214", "types": ["postal_code"], "languageCode": "en-US"}, {"longText": "2517", "shortText": "2517", "types": ["postal_code_suffix"], "languageCode": "en-US"}], "location": {"latitude": 39.7777916, "longitude": -86.2933905}, "rating": 3.4, "googleMapsUri": "https://maps.google.com/?cid=14907522291010005161&g_mp=Cilnb29nbGUubWFwcy5wbGFjZXMudjEuUGxhY2VzLlNlYXJjaE5lYXJieRACGAQgAA", "regularOpeningHours": {"openNow": false, "periods": [{"open": {"day": 0, "hour": 11, "minute": 0}, "close": {"day": 0, "hour": 21, "minute": 30}}, {"open": {"day": 2, "hour": 11, "minute": 0}, "close": {"day": 2, "hour": 21, "minute": 30}}, {"open": {"day": 3, "hour": 11, "minute": 0}, "close": {"day": 3, "hour": 21, "minute": 30}}, {"open": {"day": 4, "hour": 11, "minute": 0}, "close": {"day": 4, "hour": 21, "minute": 30}}, {"open": {"day": 5, "hour": 11, "minute": 0}, "close": {"day": 5, "hour": 21, "minute": 30}}, {"open": {"day": 6, "hour": 11, "minute": 0}, "close": {"day": 6, "hour": 21, "minute": 30}}], "weekdayDescriptions": ["Monday: Closed", "Tuesday: 11:00\u202fAM\u2009\u2013\u20099:30\u202fPM", "Wednesday: 11:00\u202fAM\u2009\u2013\u20099:30\u202fPM", "Thursday: 11:00\u202fAM\u2009\u2013\u20099:30\u202fPM", "Friday: 11:00\u202fAM\u2009\u2013\u20099:30\u202fPM", "Saturday: 11:00\u202fAM\u2009\u2013\u20099:30\u202fPM", "Sunday: 11:00\u202fAM\u2009\u2013\u20099:30\u202fPM"], "nextOpenTime": "2026-02-08T16:00:00Z"}, "businessStatus": "OPERATIONAL", "priceLevel": "PRICE_LEVEL_INEXPENSIVE", "userRatingCount": 412, "displayName": {"text": "China Buffet", "languageCode": "en"}, "takeout": true, "delivery": true, "dineIn": true}, {"id": "ChIJDd8stKiobIgRjwubUF53P0k", "nationalPhoneNumber": "(317) 273-0898", "formattedAddress": "10968 E US Hwy 36, Avon, IN 46123, USA", "addressComponents": [{"longText": "10968", "shortText": "10968", "types": ["street_number"], "languageCode": "en-US"}, {"longText": "East US Highway 36", "shortText": "E US Hwy 36", "types": ["route"], "languageCode": "en"}, {"longText": "Avon", "shortText": "Avon", "types": ["locality", "political"], "languageCode": "en"}, {"longText": "Washington Township", "shortText": "Washington Township", "types": ["administrative_area_level_3", "political"], "languageCode": "en"}, {"longText": "Hendricks County", "shortText": "Hendricks County", "types": ["administrative_area_level_2", "political"], "languageCode": "en"}, {"longText": "Indiana", "shortText": "IN", "types": ["administrative_area_level_1", "political"], "languageCode": "en"}, {"longText": "United States", "shortText": "US", "types": ["country", "political"], "languageCode": "en"}, {"longText": "46123", "shortText": "46123", "types": ["postal_code"], "languageCode": "en-US"}, {"longText": "7980", "shortText": "7980", "types": ["postal_code_suffix"], "languageCode": "en-US"}], "location": {"latitude": 39.764783099999995, "longitude": -86.3274041}, "rating": 4.3, "googleMapsUri": "https://maps.google.com/?cid=5278068535264480143&g_mp=Cilnb29nbGUubWFwcy5wbGFjZXMudjEuUGxhY2VzLlNlYXJjaE5lYXJieRACGAQgAA", "websiteUri": "http://chinabistroavon.com/", "regularOpeningHours": {"openNow": false, "periods": [{"open": {"day": 0, "hour": 11, "minute": 30}, "close": {"day": 0, "hour": 21, "minute": 0}}, {"open": {"day": 1, "hour": 11, "minute": 30}, "close": {"day": 1, "hour": 21, "minute": 0}}, {"open": {"day": 3, "hour": 11, "minute": 30}, "close": {"day": 3, "hour": 21, "minute": 0}}, {"open": {"day": 4, "hour": 11, "minute": 30}, "close": {"day": 4, "hour": 21, "minute": 0}}, {"open": {"day": 5, "hour": 11, "minute": 30}, "close": {"day": 5, "hour": 21, "minute": 0}}, {"open": {"day": 6, "hour": 11, "minute": 30}, "close": {"day": 6, "hour": 21, "minute": 0}}], "weekdayDescriptions": ["Monday: 11:30\u202fAM\u2009\u2013\u20099:00\u202fPM", "Tuesday: Closed", "Wednesday: 11:30\u202fAM\u2009\u2013\u20099:00\u202fPM", "Thursday: 11:30\u202fAM\u2009\u2013\u20099:00\u202fPM", "Friday: 11:30\u202fAM\u2009\u2013\u20099:00\u202fPM", "Saturday: 11:30\u202fAM\u2009\u2013\u20099:00\u202fPM", "Sunday: 11:30\u202fAM\u2009\u2013\u20099:00\u202fPM"], "nextOpenTime": "2026-02-08T16:30:00Z"}, "businessStatus": "OPERATIONAL", "priceLevel": "PRICE_LEVEL_INEXPENSIVE", "userRatingCount": 435, "displayName": {"text": "China Bistro", "languageCode": "en"}, "takeout": true, "delivery": true, "dineIn": true}, {"id": "ChIJ24e-N9CnbIgRrwQfmgJ25-c", "nationalPhoneNumber": "(317) 390-0688", "formattedAddress": "1221 S Girls School Rd, Indianapolis, IN 46231, USA", "addressComponents": [{"longText": "1221", "shortText": "1221", "types": ["street_number"], "languageCode": "en-US"}, {"longText": "South Girls School Road", "shortText": "S Girls School Rd", "types": ["route"], "languageCode": "en"}, {"longText": "Chapel Hill / Ben Davis", "shortText": "Chapel Hill / Ben Davis", "types": ["neighborhood", "political"], "languageCode": "en"}, {"longText": "Indianapolis", "shortText": "Indianapolis", "types": ["locality", "political"], "languageCode": "en"}, {"longText": "Wayne Township", "shortText": "Wayne Township", "types": ["administrative_area_level_3", "political"], "languageCode": "en"}, {"longText": "Marion County", "shortText": "Marion County", "types": ["administrative_area_level_2", "political"], "languageCode": "en"}, {"longText": "Indiana", "shortText": "IN", "types": ["administrative_area_level_1", "political"], "languageCode": "en"}, {"longText": "United States", "shortText": "US", "types": ["country", "political"], "languageCode": "en"}, {"longText": "46231", "shortText": "46231", "types": ["postal_code"], "languageCode": "en-US"}, {"longText": "1141", "shortText": "1141", "types": ["postal_code_suffix"], "languageCode": "en-US"}], "location": {"latitude": 39.749079200000004, "longitude": -86.2881203}, "rating": 3.9, "googleMapsUri": "https://maps.google.com/?cid=16710454695929250991&g_mp=Cilnb29nbGUubWFwcy5wbGFjZXMudjEuUGxhY2VzLlNlYXJjaE5lYXJieRACGAQgAA", "websiteUri": "http://www.goldenchinaindianapolis.com/", "regularOpeningHours": {"openNow": false, "periods": [{"open": {"day": 1, "hour": 11, "minute": 0}, "close": {"day": 1, "hour": 22, "minute": 0}}, {"open": {"day": 2, "hour": 11, "minute": 0}, "close": {"day": 2, "hour": 22, "minute": 0}}, {"open": {"day": 3, "hour": 11, "minute": 0}, "close": {"day": 3, "hour": 22, "minute": 0}}, {"open": {"day": 4, "hour": 11, "minute": 0}, "close": {"day": 4, "hour": 22, "minute": 0}}, {"open": {"day": 5, "hour": 11, "minute": 0}, "close": {"day": 5, "hour": 22, "minute": 0}}, {"open": {"day": 6, "hour": 11, "minute": 0}, "close": {"day": 6, "hour": 22, "minute": 0}}], "weekdayDescriptions": ["Monday: 11:00\u202fAM\u2009\u2013\u200910:00\u202fPM", "Tuesday: 11:00\u202fAM\u2009\u2013\u200910:00\u202fPM", "Wednesday: 11:00\u202fAM\u2009\u2013\u200910:00\u202fPM", "Thursday: 11:00\u202fAM\u2009\u2013\u200910:00\u202fPM", "Friday: 11:00\u202fAM\u2009\u2013\u200910:00\u202fPM", "Saturday: 11:00\u202fAM\u2009\u2013\u200910:00\u202fPM", "Sunday: Closed"], "nextOpenTime": "2026-02-09T16:00:00Z"}, "businessStatus": "OPERATIONAL", "priceLevel": "PRICE_LEVEL_INEXPENSIVE", "userRatingCount": 257, "displayName": {"text": "Golden China", "languageCode": "en"}, "takeout": true, "delivery": true, "dineIn": true}, {"id": "ChIJATuYDBCpbIgRyDQ8JPNWcxg", "nationalPhoneNumber": "(317) 273-8899", "formattedAddress": "7451 W 10th St, Indianapolis, IN 46214, USA", "addressComponents": [{"longText": "7451", "shortText": "7451", "types": ["street_number"], "languageCode": "en-US"}, {"longText": "West 10th Street", "shortText": "W 10th St", "types": ["route"], "languageCode": "en"}, {"longText": "Chapel Hill / Ben Davis", "shortText": "Chapel Hill / Ben Davis", "types": ["neighborhood", "political"], "languageCode": "en"}, {"longText": "Indianapolis", "shortText": "Indianapolis", "types": ["locality", "political"], "languageCode": "en"}, {"longText": "Wayne Township", "shortText": "Wayne Township", "types": ["administrative_area_level_3", "political"], "languageCode": "en"}, {"longText": "Marion County", "shortText": "Marion County", "types": ["administrative_area_level_2", "political"], "languageCode": "en"}, {"longText": "Indiana", "shortText": "IN", "types": ["administrative_area_level_1", "political"], "languageCode": "en"}, {"longText": "United States", "shortText": "US", "types": ["country", "political"], "languageCode": "en"}, {"longText": "46214", "shortText": "46214", "types": ["postal_code"], "languageCode": "en-US"}], "location": {"latitude": 39.7777031, "longitude": -86.2914705}, "googleMapsUri": "https://maps.google.com/?cid=1761847481516963016&g_mp=Cilnb29nbGUubWFwcy5wbGFjZXMudjEuUGxhY2VzLlNlYXJjaE5lYXJieRACGAQgAA", "websiteUri": "http://www.chinabuffetorder.com/", "regularOpeningHours": {"openNow": false, "periods": [{"open": {"day": 0, "hour": 11, "minute": 0}, "close": {"day": 0, "hour": 21, "minute": 0}}, {"open": {"day": 2, "hour": 11, "minute": 0}, "close": {"day": 2, "hour": 21, "minute": 0}}, {"open": {"day": 3, "hour": 11, "minute": 0}, "close": {"day": 3, "hour": 21, "minute": 0}}, {"open": {"day": 4, "hour": 11, "minute": 0}, "close": {"day": 4, "hour": 21, "minute": 0}}, {"open": {"day": 5, "hour": 11, "minute": 0}, "close": {"day": 5, "hour": 21, "minute": 0}}, {"open": {"day": 6, "hour": 11, "minute": 0}, "close": {"day": 6, "hour": 21, "minute": 0}}], "weekdayDescriptions": ["Monday: Closed", "Tuesday: 11:00\u202fAM\u2009\u2013\u20099:00\u202fPM", "Wednesday: 11:00\u202fAM\u2009\u2013\u20099:00\u202fPM", "Thursday: 11:00\u202fAM\u2009\u2013\u20099:00\u202fPM", "Friday: 11:00\u202fAM\u2009\u2013\u20099:00\u202fPM", "Saturday: 11:00\u202fAM\u2009\u2013\u20099:00\u202fPM", "Sunday: 11:00\u202fAM\u2009\u2013\u20099:00\u202fPM"], "nextOpenTime": "2026-02-08T16:00:00Z"}, "businessStatus": "OPERATIONAL", "displayName": {"text": "Chef Zhen", "languageCode": "en"}, "takeout": true, "delivery": true, "dineIn": true}]}