{"cached_at": "2026-02-08T03:27:46.076195+00:00", "request": {"lat": 32.911835135135135, "lng": -96.797, "radius": 5000}, "response": [{"id": "ChIJ3Yp_y4IgTIYRedDz34j7MFc", "nationalPhoneNumber": "(214) 361-1771", "formattedAddress": "6025 Royal Ln #201, Dallas, TX 75230, USA", "addressComponents": [{"longText": "#201", "shortText": "#201", "types": ["subpremise"], "languageCode": "en"}, {"longText": "6025", "shortText": "6025", "types": ["street_number"], "languageCode": "en-US"}, {"longText": "Royal Lane", "shortText": "Royal Ln", "types": ["route"], "languageCode": "en"}, {"longText": "North Dallas", "shortText": "North Dallas", "types": ["neighborhood", "political"], "languageCode": "en"}, {"longText": "Dallas", "shortText": "Dallas", "types": ["locality", "political"], "languageCode": "en"}, {"longText": "Dallas County", "shortText": "Dallas County", "types": ["administrative_area_level_2", "political"], "languageCode": "en"}, {"longText": "Texas", "shortText": "TX", "types": ["administrative_area_level_1", "political"], "languageCode": "en"}, {"longText": "United States", "shortText": "US", "types": ["country", "political"], "languageCode": "en"}, {"longText": "75230", "shortText": "75230", "types": ["postal_code"], "languageCode": "en-US"}], "location": {"latitude": 32.896076900000004, "longitude": -96.8021275}, "rating": 4.3, "googleMapsUri": "https://maps.google.com/?cid=6282798045473263737&g_mp=Cilnb29nbGUubWFwcy5wbGFjZXMudjEuUGxhY2VzLlNlYXJjaE5lYXJieRACGAQgAA", "websiteUri": "http://royalchinadallas.com/", "regularOpeningHours": {"openNow": true, "periods": [{"open": {"day": 0, "hour": 11, "minute": 0}, "close": {"day": 0, "hour": 14, "minute": 30}}, {"open": {"day": 0, "hour": 16, "minute": 30}, "close": {"day": 0, "hour": 21, "minute": 0}}, {"open": {"day": 1, "hour": 11, "minute": 0}, "close": {"day": 1, "hour": 14, "minute": 30}}, {"open": {"day": 1, "hour": 16, "minute": 30}, "close": {"day": 1, "hour": 21, "minute": 0}}, {"open": {"day": 2, "hour": 11, "minute": 0}, "close": {"day": 2, "hour": 14, "minute": 30}}, {"open": {"day": 2, "hour": 16, "minute": 30}, "close": {"day": 2, "hour": 21, "minute": 0}}, {"open": {"day": 3, "hour": 11, "minute": 0}, "close": {"day": 3, "hour": 14, "minute": 30}}, {"open": {"day": 3, "hour": 16, "minute": 30}, "close": {"day": 3, "hour": 21, "minute": 0}}, {"open": {"day": 4, "hour": 11, "minute": 0}, "close": {"day": 4, "hour": 14, "minute": 30}}, {"open": {"day": 4, "hour": 16, "minute": 30}, "close": {"day": 4, "hour": 21, "minute": 0}}, {"open": {"day": 5, "hour": 11, "minute": 0}, "close": {"day": 5, "hour": 14, "minute": 30}}, {"open": {"day": 5, "hour": 16, "minute": 30}, "close": {"day": 5, "hour": 21, "minute": 30}}, {"open": {"day": 6, "hour": 16, "minute": 30}, "close": {"day": 6, "hour": 21, "minute": 30}}], "weekdayDescriptions": ["Monday: 11:00\u202fAM\u2009\u2013\u20092:30\u202fPM, 4:30\u2009\u2013\u20099:00\u202fPM", "Tuesday: 11:00\u202fAM\u2009\u2013\u20092:30\u202fPM, 4:30\u2009\u2013\u20099:00\u202fPM", "Wednesday: 11:00\u202fAM\u2009\u2013\u20092:30\u202fPM, 4:30\u2009\u2013\u20099:00\u202fPM", "Thursday: 11:00\u202fAM\u2009\u2013\u20092:30\u202fPM, 4:30\u2009\u2013\u20099:00\u202fPM", "Friday: 11:00\u202fAM\u2009\u2013\u20092:30\u202fPM, 4:30\u2009\u2013\u20099:30\u202fPM", "Saturday: 4:30\u2009\u2013\u20099:30\u202fPM", "Sunday: 11:00\u202fAM\u2009\u2013\u20092:30\u202fPM, 4:30\u2009\u2013\u20099:00\u202fPM"], "nextCloseTime": "2026-02-08T03:30:00Z"}, "businessStatus": "OPERATIONAL", "priceLevel": "PRICE_LEVEL_MODERATE", "userRatingCount": 1985, "displayName": {"text": "Royal China Restaurant", "languageCode": "en"}, "takeout": true, "delivery": true, "dineIn": true}, {"id": "ChIJ-VPF5N2fToYRs-KLPEkNiAU", "nationalPhoneNumber": "(214) 890-1888", "formattedAddress": "10455 N Central Expy #123, Dallas, TX 75230, USA", "addressComponents": [{"longText": "123", "shortText": "123", "types": ["subpremise"], "languageCode": "en"}, {"longText": "10455", "shortText": "10455", "types": ["street_number"], "languageCode": "en-US"}, {"longText": "North Central Expressway", "shortText": "N Central Expy", "types": ["route"], "languageCode": "en"}, {"longText": "North Dallas", "shortText": "North Dallas", "types": ["neighborhood", "political"], "languageCode": "en"}, {"longText": "Dallas", "shortText": "Dallas", "types": ["locality", "political"], "languageCode": "en"}, {"longText": "Dallas County", "shortText": "Dallas County", "types": ["administrative_area_level_2", "political"], "languageCode": "en"}, {"longText": "Texas", "shortText": "TX", "types": ["administrative_area_level_1", "political"], "languageCode": "en"}, {"longText": "United States", "shortText": "US", "types": ["country", "political"], "languageCode": "en"}, {"longText": "75230", "shortText": "75230", "types": ["postal_code"], "languageCode": "en-US"}], "location": {"latitude": 32.889778, "longitude": -96.77180899999999}, "rating": 4, "googleMapsUri": "https://maps.google.com/?cid=398583175221863091&g_mp=Cilnb29nbGUubWFwcy5wbGFjZXMudjEuUGxhY2VzLlNlYXJjaE5lYXJieRACGAQgAA", "websiteUri": "http://www.meimeibuffet.com/", "regularOpeningHours": {"openNow": false, "periods": [{"open": {"day": 0, "hour": 11, "minute": 0}, "close": {"day": 0, "hour": 21, "minute": 0}}, {"open": {"day": 1, "hour": 11, "minute": 0}, "close": {"day": 1, "hour": 21, "minute": 0}}, {"open": {"day": 2, "hour": 11, "minute": 0}, "close": {"day": 2, "hour": 21, "minute": 0}}, {"open": {"day": 3, "hour": 11, "minute": 0}, "close": {"day": 3, "hour": 21, "minute": 0}}, {"open": {"day": 4, "hour": 11, "minute": 0}, "close": {"day": 4, "hour": 21, "minute": 0}}, {"open": {"day": 5, "hour": 11, "minute": 0}, "close": {"day": 5, "hour": 21, "minute": 0}}, {"open": {"day": 6, "hour": 11, "minute": 0}, "close": {"day": 6, "hour": 21, "minute": 0}}], "weekdayDescriptions": ["Monday: 11:00\u202fAM\u2009\u2013\u20099:00\u202fPM", "Tuesday: 11:00\u202fAM\u2009\u2013\u20099:00\u202fPM", "Wednesday: 11:00\u202fAM\u2009\u2013\u20099:00\u202fPM", "Thursday: 11:00\u202fAM\u2009\u2013\u20099:00\u202fPM", "Friday: 11:00\u202fAM\u2009\u2013\u20099:00\u202fPM", "Saturday: 11:00\u202fAM\u2009\u2013\u20099:00\u202fPM", "Sunday: 11:00\u202fAM\u2009\u2013\u20099:00\u202fPM"], "nextOpenTime": "2026-02-08T17:00:00Z"}, "businessStatus": "OPERATIONAL", "priceLevel": "PRICE_LEVEL_INEXPENSIVE", "userRatingCount": 1838, "displayName": {"text": "Mei Mei Chinese Buffet", "languageCode": "en"}, "takeout": true, "delivery": true, "dineIn": true}, {"id": "ChIJueEmOG0gTIYRqiN3AA-JmPY", "nationalPhoneNumber": "(214) 363-6655", "formattedAddress": "11617 N Central Expy Suite 135, Dallas, TX 75243, USA", "addressComponents": [{"longText": "Suite 135", "shortText": "Suite 135", "types": ["subpremise"], "languageCode": "en"}, {"longText": "11617", "shortText": "11617", "types": ["street_number"], "languageCode": "en-US"}, {"longText": "North Central Expressway", "shortText": "N Central Expy", "types": ["route"], "languageCode": "en"}, {"longText": "North Dallas", "shortText": "North Dallas", "types": ["neighborhood", "political"], "languageCode": "en"}, {"longText": "Dallas", "shortText": "Dallas", "types": ["locality", "political"], "languageCode": "en"}, {"longText": "Dallas County", "shortText": "Dallas County", "types": ["administrative_area_level_2", "political"], "languageCode": "en"}, {"longText": "Texas", "shortText": "TX", "types": ["administrative_area_level_1", "political"], "languageCode": "en"}, {"longText": "United States", "shortText": "US", "types": ["country", "political"], "languageCode": "en"}, {"longText": "75243", "shortText": "75243", "types": ["postal_code"], "languageCode": "en-US"}], "location": {"latitude": 32.9085033, "longitude": -96.7714653}, "rating": 4.6, "googleMapsUri": "https://maps.google.com/?cid=17769103027315614634&g_mp=Cilnb29nbGUubWFwcy5wbGFjZXMudjEuUGxhY2VzLlNlYXJjaE5lYXJieRACGAQgAA", "websiteUri": "https://asianmint.com/asianmintforestlane?utm_source=google", "regularOpeningHours": {"openNow": true, "periods": [{"open": {"day": 0, "hour": 11, "minute": 0}, "close": {"day": 0, "hour": 21, "minute": 0}}, {"open": {"day": 1, "hour": 11, "minute": 0}, "close": {"day": 1, "hour": 21, "minute": 0}}, {"open": {"day": 2, "hour": 11, "minute": 0}, "close": {"day": 2, "hour": 21, "minute": 0}}, {"open": {"day": 3, "hour": 11, "minute": 0}, "close": {"day": 3, "hour": 21, "minute": 0}}, {"open": {"day": 4, "hour": 11, "minute": 0}, "close": {"day": 4, "hour": 21, "minute": 0}}, {"open": {"day": 5, "hour": 11, "minute": 0}, "close": {"day": 5, "hour": 21, "minute": 30}}, {"open": {"day": 6, "hour": 11, "minute": 0}, "close": {"day": 6, "hour": 21, "minute": 30}}], "weekdayDescriptions": ["Monday: 11:00\u202fAM\u2009\u2013\u20099:00\u202fPM", "Tuesday: 11:00\u202fAM\u2009\u2013\u20099:00\u202fPM", "Wednesday: 11:00\u202fAM\u2009\u2013\u20099:00\u202fPM", "Thursday: 11:00\u202fAM\u2009\u2013\u20099:00\u202fPM", "Friday: 11:00\u202fAM\u2009\u2013\u20099:30\u202fPM", "Saturday: 11:00\u202fAM\u2009\u2013\u20099:30\u202fPM", "Sunday: 11:00\u202fAM\u2009\u2013\u20099:00\u202fPM"], "nextCloseTime": "2026-02-08T03:30:00Z"}, "businessStatus": "OPERATIONAL", "priceLevel": "PRICE_LEVEL_MODERATE", "userRatingCount": 2017, "displayName": {"text": "Asian Mint", "languageCode": "en"}, "takeout": true, "delivery": true, "dineIn": true}, {"id": "ChIJ3xJUndCfToYRxnGoPJHqt7w", "nationalPhoneNumber": "(972) 961-1168", "formattedAddress": "8041 Walnut Hill Ln suite 854, Dallas, TX 75231, USA", "addressComponents": [{"longText": "suite 854", "shortText": "suite 854", "types": ["subpremise"], "languageCode": "en"}, {"longText": "8041", "shortText": "8041", "types": ["street_number"], "languageCode": "en-US"}, {"longText": "Walnut Hill Lane", "shortText": "Walnut Hill Ln", "types": ["route"], "languageCode": "en"}, {"longText": "Vickery Meadow", "shortText": "Vickery Meadow", "types": ["neighborhood", "political"], "languageCode": "en"}, {"longText": "Dallas", "shortText": "Dallas", "types": ["locality", "political"], "languageCode": "en"}, {"longText": "Dallas County", "shortText": "Dallas County", "types": ["administrative_area_level_2", "political"], "languageCode": "en"}, {"longText": "Texas", "shortText": "TX", "types": ["administrative_area_level_1", "political"], "languageCode": "en"}, {"longText": "United States", "shortText": "US", "types": ["country", "political"], "languageCode": "en"}, {"longText": "75231", "shortText": "75231", "types": ["postal_code"], "languageCode": "en-US"}], "location": {"latitude": 32.881622, "longitude": -96.7675478}, "rating": 4.3, "googleMapsUri": "https://maps.google.com/?cid=13598595509377331654&g_mp=Cilnb29nbGUubWFwcy5wbGFjZXMudjEuUGxhY2VzLlNlYXJjaE5lYXJieRACGAQgAA", "websiteUri": "https://wokstarchinese.com/", "regularOpeningHours": {"openNow": true, "periods": [{"open": {"day": 0, "hour": 11, "minute": 0}, "close": {"day": 0, "hour": 21, "minute": 0}}, {"open": {"day": 1, "hour": 11, "minute": 0}, "close": {"day": 1, "hour": 21, "minute": 0}}, {"open": {"day": 2, "hour": 11, "minute": 0}, "close": {"day": 2, "hour": 21, "minute": 0}}, {"open": {"day": 3, "hour": 11, "minute": 0}, "close": {"day": 3, "hour": 21, "minute": 0}}, {"open": {"day": 4, "hour": 11, "minute": 0}, "close": {"day": 4, "hour": 21, "minute": 0}}, {"open": {"day": 5, "hour": 11, "minute": 0}, "close": {"day": 5, "hour": 22, "minute": 0}}, {"open": {"day": 6, "hour": 11, "minute": 0}, "close": {"day": 6, "hour": 22, "minute": 0}}], "weekdayDescriptions": ["Monday: 11:00\u202fAM\u2009\u2013\u20099:00\u202fPM", "Tuesday: 11:00\u202fAM\u2009\u2013\u20099:00\u202fPM", "Wednesday: 11:00\u202fAM\u2009\u2013\u20099:00\u202fPM", "Thursday: 11:00\u202fAM\u2009\u2013\u20099:00\u202fPM", "Friday: 11:00\u202fAM\u2009\u2013\u200910:00\u202fPM", "Saturday: 11:00\u202fAM\u2009\u2013\u200910:00\u202fPM", "Sunday: 11:00\u202fAM\u2009\u2013\u20099:00\u202fPM"], "nextCloseTime": "2026-02-08T04:00:00Z"}, "businessStatus": "OPERATIONAL", "priceLevel": "PRICE_LEVEL_MODERATE", "userRatingCount": 782, "displayName": {"text": "Wok Star Chinese", "languageCode": "en"}, "takeout": true, "delivery": true, "dineIn": true}, {"id": "ChIJY8APiCYhTIYRbU-GGp2wtBw", "nationalPhoneNumber": "(972) 863-7575", "formattedAddress": "5365 Spring Valley Rd STE 158, Dallas, TX 75254, USA", "addressComponents": [{"longText": "STE 158", "shortText": "STE 158", "types": ["subpremise"], "languageCode": "en"}, {"longText": "5365", "shortText": "5365", "types": ["street_number"], "languageCode": "en-US"}, {"longText": "Spring Valley Road", "shortText": "Spring Valley Rd", "types": ["route"], "languageCode": "en"}, {"longText": "Far North Dallas", "shortText": "Far North Dallas", "types": ["neighborhood", "political"], "languageCode": "en"}, {"longText": "Dallas", "shortText": "Dallas", "types": ["locality", "political"], "languageCode": "en"}, {"longText": "Dallas County", "shortText": "Dallas County", "types": ["administrative_area_level_2", "political"], "languageCode": "en"}, {"longText": "Texas", "shortText": "TX", "types": ["administrative_area_level_1", "political"], "languageCode": "en"}, {"longText": "United States", "shortText": "US", "types": ["country", "political"], "languageCode": "en"}, {"longText": "75254", "shortText": "75254", "types": ["postal_code"], "languageCode": "en-US"}], "location": {"latitude": 32.939841799999996, "longitude": -96.81568779999999}, "rating": 4.5, "googleMapsUri": "https://maps.google.com/?cid=2068472317671264109&g_mp=Cilnb29nbGUubWFwcy5wbGFjZXMudjEuUGxhY2VzLlNlYXJjaE5lYXJieRACGAQgAA", "websiteUri": "http://www.sabaidee.us/", "regularOpeningHours": {"openNow": true, "periods": [{"open": {"day": 0, "hour": 11, "minute": 0}, "close": {"day": 0, "hour": 21, "minute": 30}}, {"open": {"day": 1, "hour": 11, "minute": 0}, "close": {"day": 1, "hour": 21, "minute": 30}}, {"open": {"day": 2, "hour": 11, "minute": 0}, "close": {"day": 2, "hour": 21, "minute": 30}}, {"open": {"day": 3, "hour": 11, "minute": 0}, "close": {"day": 3, "hour": 21, "minute": 30}}, {"open": {"day": 4, "hour": 11, "minute": 0}, "close": {"day": 4, "hour": 21, "minute": 30}}, {"open": {"day": 5, "hour": 11, "minute": 0}, "close": {"day": 5, "hour": 21, "minute": 30}}, {"open": {"day": 6, "hour": 11, "minute": 0}, "close": {"day": 6, "hour": 21, "minute": 30}}], "weekdayDescriptions": ["Monday: 11:00\u202fAM\u2009\u2013\u20099:30\u202fPM", "Tuesday: 11:00\u202fAM\u2009\u2013\u20099:30\u202fPM", "Wednesday: 11:00\u202fAM\u2009\u2013\u20099:30\u202fPM", "Thursday: 11:00\u202fAM\u2009\u2013\u20099:30\u202fPM", "Friday: 11:00\u202fAM\u2009\u2013\u20099:30\u202fPM", "Saturday: 11:00\u202fAM\u2009\u2013\u20099:30\u202fPM", "Sunday: 11:00\u202fAM\u2009\u2013\u20099:30\u202fPM"], "nextCloseTime": "2026-02-08T03:30:00Z"}, "businessStatus": "OPERATIONAL", "priceLevel": "PRICE_LEVEL_MODERATE", "userRatingCount": 710, "displayName": {"text": "Sabaidee Lao & Thai Street Food - Addison", "languageCode": "en"}, "takeout": true, "delivery": true, "dineIn": true}, {"id": "ChIJy06ZhNsgTIYRvSN6xd7i69o", "nationalPhoneNumber": "(972) 490-6338", "formattedAddress": "13350 Dallas Pkwy SUITE 915, Dallas, TX 75240, USA", "addressComponents": [{"longText": "SUITE 915", "shortText": "SUITE 915", "types": ["subpremise"], "languageCode": "en"}, {"longText": "13350", "shortText": "13350", "types": ["street_number"], "languageCode": "en-US"}, {"longText": "Dallas Parkway", "shortText": "Dallas Pkwy", "types": ["route"], "languageCode": "en"}, {"longText": "Dallas International District", "shortText": "Dallas International District", "types": ["neighborhood", "political"], "languageCode": "en"}, {"longText": "Dallas", "shortText": "Dallas", "types": ["locality", "political"], "languageCode": "en"}, {"longText": "Dallas County", "shortText": "Dallas County", "types": ["administrative_area_level_2", "political"], "languageCode": "en"}, {"longText": "Texas", "shortText": "TX", "types": ["administrative_area_level_1", "political"], "languageCode": "en"}, {"longText": "United States", "shortText": "US", "types": ["country", "political"], "languageCode": "en"}, {"longText": "75240", "shortText": "75240", "types": ["postal_code"], "languageCode": "en-US"}], "location": {"latitude": 32.9302206, "longitude": -96.8194206}, "rating": 3.6, "googleMapsUri": "https://maps.google.com/?cid=15774951566219027389&g_mp=Cilnb29nbGUubWFwcy5wbGFjZXMudjEuUGxhY2VzLlNlYXJjaE5lYXJieRACGAQgAA", "websiteUri": "https://www.pandaexpress.com/locations/tx/dallas/1819", "regularOpeningHours": {"openNow": false, "periods": [{"open": {"day": 0, "hour": 12, "minute": 0}, "close": {"day": 0, "hour": 18, "minute": 0}}, {"open": {"day": 1, "hour": 10, "minute": 30}, "close": {"day": 1, "hour": 20, "minute": 0}}, {"open": {"day": 2, "hour": 10, "minute": 30}, "close": {"day": 2, "hour": 20, "minute": 0}}, {"open": {"day": 3, "hour": 10, "minute": 30}, "close": {"day": 3, "hour": 20, "minute": 0}}, {"open": {"day": 4, "hour": 10, "minute": 30}, "close": {"day": 4, "hour": 20, "minute": 0}}, {"open": {"day": 5, "hour": 10, "minute": 30}, "close": {"day": 5, "hour": 20, "minute": 0}}, {"open": {"day": 6, "hour": 10, "minute": 30}, "close": {"day": 6, "hour": 20, "minute": 0}}], "weekdayDescriptions": ["Monday: 10:30\u202fAM\u2009\u2013\u20098:00\u202fPM", "Tuesday: 10:30\u202fAM\u2009\u2013\u20098:00\u202fPM", "Wednesday: 10:30\u202fAM\u2009\u2013\u20098:00\u202fPM", "Thursday: 10:30\u202fAM\u2009\u2013\u20098:00\u202fPM", "Friday: 10:30\u202fAM\u2009\u2013\u20098:00\u202fPM", "Saturday: 10:30\u202fAM\u2009\u2013\u20098:00\u202fPM", "Sunday: 12:00\u2009\u2013\u20096:00\u202fPM"], "nextOpenTime": "2026-02-08T18:00:00Z"}, "businessStatus": "OPERATIONAL", "priceLevel": "PRICE_LEVEL_INEXPENSIVE", "userRatingCount": 251, "displayName": {"text": "Panda Express", "languageCode": "en"}, "takeout": true, "delivery": true, "dineIn": true}, {"id": "ChIJP6F4CwwhTIYRHhKRktwX3ss", "nationalPhoneNumber": "(214) 242-9368", "formattedAddress": "5290 Belt Line Rd #118, Dallas, TX 75254, USA", "addressComponents": [{"longText": "118", "shortText": "118", "types": ["subpremise"], "languageCode": "en"}, {"longText": "5290", "shortText": "5290", "types": ["street_number"], "languageCode": "en-US"}, {"longText": "Belt Line Road", "shortText": "Belt Line Rd", "types": ["route"], "languageCode": "en"}, {"longText": "Dallas", "shortText": "Dallas", "types": ["locality", "political"], "languageCode": "en"}, {"longText": "Dallas County", "shortText": "Dallas County", "types": ["administrative_area_level_2", "political"], "languageCode": "en"}, {"longText": "Texas", "shortText": "TX", "types": ["administrative_area_level_1", "political"], "languageCode": "en"}, {"longText": "United States", "shortText": "US", "types": ["country", "political"], "languageCode": "en"}, {"longText": "75254", "shortText": "75254", "types": ["postal_code"], "languageCode": "en-US"}], "location": {"latitude": 32.9534089, "longitude": -96.81666360000001}, "rating": 4.8, "googleMapsUri": "https://maps.google.com/?cid=14690205270648361502&g_mp=Cilnb29nbGUubWFwcy5wbGFjZXMudjEuUGxhY2VzLlNlYXJjaE5lYXJieRACGAQgAA", "websiteUri": "https://asianmint.com/asianmintaddison?utm_source=google", "regularOpeningHours": {"openNow": true, "periods": [{"open": {"day": 1, "hour": 11, "minute": 0}, "close": {"day": 1, "hour": 15, "minute": 0}}, {"open": {"day": 1, "hour": 17, "minute": 0}, "close": {"day": 1, "hour": 21, "minute": 0}}, {"open": {"day": 2, "hour": 11, "minute": 0}, "close": {"day": 2, "hour": 15, "minute": 0}}, {"open": {"day": 2, "hour": 17, "minute": 0}, "close": {"day": 2, "hour": 21, "minute": 0}}, {"open": {"day": 3, "hour": 11, "minute": 0}, "close": {"day": 3, "hour": 15, "minute": 0}}, {"open": {"day": 3, "hour": 17, "minute": 0}, "close": {"day": 3, "hour": 21, "minute": 0}}, {"open": {"day": 4, "hour": 11, "minute": 0}, "close": {"day": 4, "hour": 15, "minute": 0}}, {"open": {"day": 4, "hour": 17, "minute": 0}, "close": {"day": 4, "hour": 21, "minute": 0}}, {"open": {"day": 5, "hour": 11, "minute": 0}, "close": {"day": 5, "hour": 15, "minute": 0}}, {"open": {"day": 5, "hour": 17, "minute": 0}, "close": {"day": 5, "hour": 21, "minute": 30}}, {"open": {"day": 6, "hour": 11, "minute": 0}, "close": {"day": 6, "hour": 21, "minute": 30}}], "weekdayDescriptions": ["Monday: 11:00\u202fAM\u2009\u2013\u20093:00\u202fPM, 5:00\u2009\u2013\u20099:00\u202fPM", "Tuesday: 11:00\u202fAM\u2009\u2013\u20093:00\u202fPM, 5:00\u2009\u2013\u20099:00\u202fPM", "Wednesday: 11:00\u202fAM\u2009\u2013\u20093:00\u202fPM, 5:00\u2009\u2013\u20099:00\u202fPM", "Thursday: 11:00\u202fAM\u2009\u2013\u20093:00\u202fPM, 5:00\u2009\u2013\u20099:00\u202fPM", "Friday: 11:00\u202fAM\u2009\u2013\u20093:00\u202fPM, 5:00\u2009\u2013\u20099:30\u202fPM", "Saturday: 11:00\u202fAM\u2009\u2013\u20099:30\u202fPM", "Sunday: Closed"], "nextCloseTime": "2026-02-08T03:30:00Z"}, "businessStatus": "OPERATIONAL", "priceLevel": "PRICE_LEVEL_MODERATE", "userRatingCount": 372, "displayName": {"text": "Asian Mint Addison", "languageCode": "en"}, "takeout": true, "delivery": true, "dineIn": true}, {"id": "ChIJkSDCpFAhTIYRjDhpbTwNIoQ", "nationalPhoneNumber": "(469) 580-6838", "formattedAddress": "12300 Inwood Rd #180, Dallas, TX 75244, USA", "addressComponents": [{"longText": "#180", "shortText": "#180", "types": ["subpremise"], "languageCode": "en"}, {"longText": "12300", "shortText": "12300", "types": ["street_number"], "languageCode": "en-US"}, {"longText": "Inwood Road", "shortText": "Inwood Rd", "types": ["route"], "languageCode": "en"}, {"longText": "Northwest Dallas", "shortText": "Northwest Dallas", "types": ["neighborhood", "political"], "languageCode": "en"}, {"longText": "Dallas", "shortText": "Dallas", "types": ["locality", "political"], "languageCode": "en"}, {"longText": "Dallas County", "shortText": "Dallas County", "types": ["administrative_area_level_2", "political"], "languageCode": "en"}, {"longText": "Texas", "shortText": "TX", "types": ["administrative_area_level_1", "political"], "languageCode": "en"}, {"longText": "United States", "shortText": "US", "types": ["country", "political"], "languageCode": "en"}, {"longText": "75244", "shortText": "75244", "types": ["postal_code"], "languageCode": "en-US"}], "location": {"latitude": 32.91553, "longitude": -96.81741439999999}, "rating": 4.5, "googleMapsUri": "https://maps.google.com/?cid=9521187115399461004&g_mp=Cilnb29nbGUubWFwcy5wbGFjZXMudjEuUGxhY2VzLlNlYXJjaE5lYXJieRACGAQgAA", "websiteUri": "http://onesandallas.com/", "regularOpeningHours": {"openNow": true, "periods": [{"open": {"day": 1, "hour": 16, "minute": 0}, "close": {"day": 1, "hour": 21, "minute": 0}}, {"open": {"day": 2, "hour": 16, "minute": 0}, "close": {"day": 2, "hour": 21, "minute": 0}}, {"open": {"day": 3, "hour": 16, "minute": 0}, "close": {"day": 3, "hour": 21, "minute": 0}}, {"open": {"day": 4, "hour": 16, "minute": 0}, "close": {"day": 4, "hour": 21, "minute": 0}}, {"open": {"day": 5, "hour": 16, "minute": 0}, "close": {"day": 5, "hour": 22, "minute": 0}}, {"open": {"day": 6, "hour": 16, "minute": 0}, "close": {"day": 6, "hour": 22, "minute": 0}}], "weekdayDescriptions": ["Monday: 4:00\u2009\u2013\u20099:00\u202fPM", "Tuesday: 4:00\u2009\u2013\u20099:00\u202fPM", "Wednesday: 4:00\u2009\u2013\u20099:00\u202fPM", "Thursday: 4:00\u2009\u2013\u20099:00\u202fPM", "Friday: 4:00\u2009\u2013\u200910:00\u202fPM", "Saturday: 4:00\u2009\u2013\u200910:00\u202fPM", "Sunday: Closed"], "nextCloseTime": "2026-02-08T04:00:00Z"}, "businessStatus": "OPERATIONAL", "priceLevel": "PRICE_LEVEL_MODERATE", "userRatingCount": 140, "displayName": {"text": "On\u0113san Dim Sum Sushi", "languageCode": "en"}, "takeout": true, "delivery": true, "dineIn": true}, {"id": "ChIJKwaAPyAhTIYRnEbIyC1htD8", "nationalPhoneNumber": "(972) 788-0101", "formattedAddress": "5365 Spring Valley Rd, Dallas, TX 75254, USA", "addressComponents": [{"longText": "5365", "shortText": "5365", "types": ["street_number"], "languageCode": "en-US"}, {"longText": "Spring Valley Road", "shortText": "Spring Valley Rd", "types": ["route"], "languageCode": "en"}, {"longText": "Far North Dallas", "shortText": "Far North Dallas", "types": ["neighborhood", "political"], "languageCode": "en"}, {"longText": "Dallas", "shortText": "Dallas", "types": ["locality", "political"], "languageCode": "en"}, {"longText": "Dallas County", "shortText": "Dallas County", "types": ["administrative_area_level_2", "political"], "languageCode": "en"}, {"longText": "Texas", "shortText": "TX", "types": ["administrative_area_level_1", "political"], "languageCode": "en"}, {"longText": "United States", "shortText": "US", "types": ["country", "political"], "languageCode": "en"}, {"longText": "75254", "shortText": "75254", "types": ["postal_code"], "languageCode": "en-US"}, {"longText": "3003", "shortText": "3003", "types": ["postal_code_suffix"], "languageCode": "en-US"}], "location": {"latitude": 32.9398251, "longitude": -96.815304}, "rating": 4, "googleMapsUri": "https://maps.google.com/?cid=4590400769467369116&g_mp=Cilnb29nbGUubWFwcy5wbGFjZXMudjEuUGxhY2VzLlNlYXJjaE5lYXJieRACGAQgAA", "regularOpeningHours": {"openNow": true, "periods": [{"open": {"day": 0, "hour": 11, "minute": 0}, "close": {"day": 0, "hour": 21, "minute": 30}}, {"open": {"day": 1, "hour": 11, "minute": 0}, "close": {"day": 1, "hour": 22, "minute": 0}}, {"open": {"day": 2, "hour": 11, "minute": 0}, "close": {"day": 2, "hour": 22, "minute": 0}}, {"open": {"day": 3, "hour": 11, "minute": 0}, "close": {"day": 3, "hour": 22, "minute": 0}}, {"open": {"day": 4, "hour": 11, "minute": 0}, "close": {"day": 4, "hour": 22, "minute": 0}}, {"open": {"day": 5, "hour": 11, "minute": 0}, "close": {"day": 5, "hour": 22, "minute": 0}}, {"open": {"day": 6, "hour": 11, "minute": 0}, "close": {"day": 6, "hour": 22, "minute": 0}}], "weekdayDescriptions": ["Monday: 11:00\u202fAM\u2009\u2013\u200910:00\u202fPM", "Tuesday: 11:00\u202fAM\u2009\u2013\u200910:00\u202fPM", "Wednesday: 11:00\u202fAM\u2009\u2013\u200910:00\u202fPM", "Thursday: 11:00\u202fAM\u2009\u2013\u200910:00\u202fPM", "Friday: 11:00\u202fAM\u2009\u2013\u200910:00\u202fPM", "Saturday: 11:00\u202fAM\u2009\u2013\u200910:00\u202fPM", "Sunday: 11:00\u202fAM\u2009\u2013\u20099:30\u202fPM"], "nextCloseTime": "2026-02-08T04:00:00Z"}, "businessStatus": "OPERATIONAL", "priceLevel": "PRICE_LEVEL_INEXPENSIVE", "userRatingCount": 420, "displayName": {"text": "Asian Star Restaurant", "languageCode": "en"}, "takeout": true, "delivery": true, "dineIn": true}, {"id": "ChIJ4808XTUgTIYR0xnHQGofHoM", "nationalPhoneNumber": "(972) 386-8083", "formattedAddress": "14050 Peyton Dr, Dallas, TX 75240, USA", "addressComponents": [{"longText": "14050", "shortText": "14050", "types": ["street_number"], "languageCode": "en-US"}, {"longText": "Peyton Drive", "shortText": "Peyton Dr", "types": ["route"], "languageCode": "en"}, {"longText": "Far North Dallas", "shortText": "Far North Dallas", "types": ["neighborhood", "political"], "languageCode": "en"}, {"longText": "Dallas", "shortText": "Dallas", "types": ["locality", "political"], "languageCode": "en"}, {"longText": "Dallas County", "shortText": "Dallas County", "types": ["administrative_area_level_2", "political"], "languageCode": "en"}, {"longText": "Texas", "shortText": "TX", "types": ["administrative_area_level_1", "political"], "languageCode": "en"}, {"longText": "United States", "shortText": "US", "types": ["country", "political"], "languageCode": "en"}, {"longText": "75240", "shortText": "75240", "types": ["postal_code"], "languageCode": "en-US"}, {"longText": "3719", "shortText": "3719", "types": ["postal_code_suffix"], "languageCode": "en-US"}], "location": {"latitude": 32.9394521, "longitude": -96.77019519999999}, "rating": 3.9, "googleMapsUri": "https://maps.google.com/?cid=9448023609483663827&g_mp=Cilnb29nbGUubWFwcy5wbGFjZXMudjEuUGxhY2VzLlNlYXJjaE5lYXJieRACGAQgAA", "websiteUri": "http://www.eggrollexpressdallas.com/", "regularOpeningHours": {"openNow": true, "periods": [{"open": {"day": 0, "hour": 8, "minute": 0}, "close": {"day": 0, "hour": 22, "minute": 0}}, {"open": {"day": 1, "hour": 8, "minute": 0}, "close": {"day": 1, "hour": 22, "minute": 0}}, {"open": {"day": 2, "hour": 8, "minute": 0}, "close": {"day": 2, "hour": 22, "minute": 0}}, {"open": {"day": 3, "hour": 8, "minute": 0}, "close": {"day": 3, "hour": 22, "minute": 0}}, {"open": {"day": 4, "hour": 8, "minute": 0}, "close": {"day": 4, "hour": 22, "minute": 0}}, {"open": {"day": 5, "hour": 8, "minute": 0}, "close": {"day": 5, "hour": 22, "minute": 0}}, {"open": {"day": 6, "hour": 8, "minute": 0}, "close": {"day": 6, "hour": 22, "minute": 0}}], "weekdayDescriptions": ["Monday: 8:00\u202fAM\u2009\u2013\u200910:00\u202fPM", "Tuesday: 8:00\u202fAM\u2009\u2013\u200910:00\u202fPM", "Wednesday: 8:00\u202fAM\u2009\u2013\u200910:00\u202fPM", "Thursday: 8:00\u202fAM\u2009\u2013\u200910:00\u202fPM", "Friday: 8:00\u202fAM\u2009\u2013\u200910:00\u202fPM", "Saturday: 8:00\u202fAM\u2009\u2013\u200910:00\u202fPM", "Sunday: 8:00\u202fAM\u2009\u2013\u200910:00\u202fPM"], "nextCloseTime": "2026-02-08T04:00:00Z"}, "businessStatus": "OPERATIONAL", "priceLevel": "PRICE_LEVEL_INEXPENSIVE", "userRatingCount": 773, "displayName": {"text": "Eggroll Express", "languageCode": "en"}, "takeout": true, "dineIn": true}, {"id": "ChIJ4RIyxNUmTIYRqverxICSR2o", "nationalPhoneNumber": "(972) 239-8880", "formattedAddress": "13901 Midway Rd # 109, Farmers Branch, TX 75244, USA", "addressComponents": [{"longText": "# 109", "shortText": "# 109", "types": ["subpremise"], "languageCode": "en"}, {"longText": "13901", "shortText": "13901", "types": ["street_number"], "languageCode": "en-US"}, {"longText": "Midway Road", "shortText": "Midway Rd", "types": ["route"], "languageCode": "en"}, {"longText": "Farmers Branch", "shortText": "Farmers Branch", "types": ["locality", "political"], "languageCode": "en"}, {"longText": "Dallas County", "shortText": "Dallas County", "types": ["administrative_area_level_2", "political"], "languageCode": "en"}, {"longText": "Texas", "shortText": "TX", "types": ["administrative_area_level_1", "political"], "languageCode": "en"}, {"longText": "United States", "shortText": "US", "types": ["country", "political"], "languageCode": "en"}, {"longText": "75244", "shortText": "75244", "types": ["postal_code"], "languageCode": "en-US"}], "location": {"latitude": 32.9389846, "longitude": -96.8396472}, "rating": 3.8, "googleMapsUri": "https://maps.google.com/?cid=7658250773119891370&g_mp=Cilnb29nbGUubWFwcy5wbGFjZXMudjEuUGxhY2VzLlNlYXJjaE5lYXJieRACGAQgAA", "websiteUri": "http://royalchopstix.com/", "regularOpeningHours": {"openNow": false, "periods": [{"open": {"day": 1, "hour": 11, "minute": 0}, "close": {"day": 1, "hour": 20, "minute": 0}}, {"open": {"day": 2, "hour": 11, "minute": 0}, "close": {"day": 2, "hour": 20, "minute": 0}}, {"open": {"day": 3, "hour": 11, "minute": 0}, "close": {"day": 3, "hour": 20, "minute": 0}}, {"open": {"day": 4, "hour": 11, "minute": 0}, "close": {"day": 4, "hour": 20, "minute": 0}}, {"open": {"day": 5, "hour": 11, "minute": 0}, "close": {"day": 5, "hour": 20, "minute": 0}}, {"open": {"day": 6, "hour": 11, "minute": 0}, "close": {"day": 6, "hour": 20, "minute": 0}}], "weekdayDescriptions": ["Monday: 11:00\u202fAM\u2009\u2013\u20098:00\u202fPM", "Tuesday: 11:00\u202fAM\u2009\u2013\u20098:00\u202fPM", "Wednesday: 11:00\u202fAM\u2009\u2013\u20098:00\u202fPM", "Thursday: 11:00\u202fAM\u2009\u2013\u20098:00\u202fPM", "Friday: 11:00\u202fAM\u2009\u2013\u20098:00\u202fPM", "Saturday: 11:00\u202fAM\u2009\u2013\u20098:00\u202fPM", "Sunday: Closed"], "nextOpenTime": "2026-02-09T17:00:00Z"}, "businessStatus": "OPERATIONAL", "priceLevel": "PRICE_LEVEL_INEXPENSIVE", "userRatingCount": 284, "displayName": {"text": "Royal Chopstix", "languageCode": "en"}, "takeout": true, "delivery": true, "dineIn": true}, {"id": "ChIJJ_4aQR0gTIYRAqi58YPYIO4", "nationalPhoneNumber": "(972) 699-0603", "formattedAddress": "9025 Forest Ln, Dallas, TX 75243, USA", "addressComponents": [{"longText": "9025", "shortText": "9025", "types": ["street_number"], "languageCode": "en-US"}, {"longText": "Forest Lane", "shortText": "Forest Ln", "types": ["route"], "languageCode": "en"}, {"longText": "Lake Highlands", "shortText": "Lake Highlands", "types": ["neighborhood", "political"], "languageCode": "en"}, {"longText": "Dallas", "shortText": "Dallas", "types": ["locality", "political"], "languageCode": "en"}, {"longText": "Dallas County", "shortText": "Dallas County", "types": ["administrative_area_level_2", "political"], "languageCode": "en"}, {"longText": "Texas", "shortText": "TX", "types": ["administrative_area_level_1", "political"], "languageCode": "en"}, {"longText": "United States", "shortText": "US", "types": ["country", "political"], "languageCode": "en"}, {"longText": "75243", "shortText": "75243", "types": ["postal_code"], "languageCode": "en-US"}, {"longText": "4195", "shortText": "4195", "types": ["postal_code_suffix"], "languageCode": "en-US"}], "location": {"latitude": 32.9096125, "longitude": -96.7481909}, "rating": 4.4, "googleMapsUri": "https://maps.google.com/?cid=17158952641489381378&g_mp=Cilnb29nbGUubWFwcy5wbGFjZXMudjEuUGxhY2VzLlNlYXJjaE5lYXJieRACGAQgAA", "regularOpeningHours": {"openNow": false, "periods": [{"open": {"day": 1, "hour": 11, "minute": 0}, "close": {"day": 1, "hour": 18, "minute": 0}}, {"open": {"day": 2, "hour": 11, "minute": 0}, "close": {"day": 2, "hour": 18, "minute": 0}}, {"open": {"day": 3, "hour": 11, "minute": 0}, "close": {"day": 3, "hour": 18, "minute": 0}}, {"open": {"day": 4, "hour": 11, "minute": 0}, "close": {"day": 4, "hour": 18, "minute": 0}}, {"open": {"day": 5, "hour": 11, "minute": 0}, "close": {"day": 5, "hour": 18, "minute": 0}}, {"open": {"day": 6, "hour": 11, "minute": 0}, "close": {"day": 6, "hour": 15, "minute": 0}}], "weekdayDescriptions": ["Monday: 11:00\u202fAM\u2009\u2013\u20096:00\u202fPM", "Tuesday: 11:00\u202fAM\u2009\u2013\u20096:00\u202fPM", "Wednesday: 11:00\u202fAM\u2009\u2013\u20096:00\u202fPM", "Thursday: 11:00\u202fAM\u2009\u2013\u20096:00\u202fPM", "Friday: 11:00\u202fAM\u2009\u2013\u20096:00\u202fPM", "Saturday: 11:00\u202fAM\u2009\u2013\u20093:00\u202fPM", "Sunday: Closed"], "nextOpenTime": "2026-02-09T17:00:00Z"}, "businessStatus": "OPERATIONAL", "priceLevel": "PRICE_LEVEL_INEXPENSIVE", "userRatingCount": 198, "displayName": {"text": "Gourmet China Restaurant", "languageCode": "en"}, "takeout": true, "dineIn": true}, {"id": "ChIJm_AvaWwgTIYRcM6ECQA9Mks", "nationalPhoneNumber": "(972) 566-6030", "formattedAddress": "7777 Forest Ln, Dallas, TX 75230, USA", "addressComponents": [{"longText": "7777", "shortText": "7777", "types": ["street_number"], "languageCode": "en-US"}, {"longText": "Forest Lane", "shortText": "Forest Ln", "types": ["route"], "languageCode": "en"}, {"longText": "North Dallas", "shortText": "North Dallas", "types": ["neighborhood", "political"], "languageCode": "en"}, {"longText": "Dallas", "shortText": "Dallas", "types": ["locality", "political"], "languageCode": "en"}, {"longText": "Dallas County", "shortText": "Dallas County", "types": ["administrative_area_level_2", "political"], "languageCode": "en"}, {"longText": "Texas", "shortText": "TX", "types": ["administrative_area_level_1", "political"], "languageCode": "en"}, {"longText": "United States", "shortText": "US", "types": ["country", "political"], "languageCode": "en"}, {"longText": "75230", "shortText": "75230", "types": ["postal_code"], "languageCode": "en-US"}], "location": {"latitude": 32.9113295, "longitude": -96.77434869999999}, "rating": 4.3, "googleMapsUri": "https://maps.google.com/?cid=5418460372049120880&g_mp=Cilnb29nbGUubWFwcy5wbGFjZXMudjEuUGxhY2VzLlNlYXJjaE5lYXJieRACGAQgAA", "regularOpeningHours": {"openNow": false, "periods": [{"open": {"day": 1, "hour": 10, "minute": 30}, "close": {"day": 1, "hour": 19, "minute": 0}}, {"open": {"day": 2, "hour": 10, "minute": 30}, "close": {"day": 2, "hour": 19, "minute": 0}}, {"open": {"day": 3, "hour": 10, "minute": 30}, "close": {"day": 3, "hour": 19, "minute": 0}}, {"open": {"day": 4, "hour": 10, "minute": 30}, "close": {"day": 4, "hour": 19, "minute": 0}}, {"open": {"day": 5, "hour": 10, "minute": 30}, "close": {"day": 5, "hour": 19, "minute": 0}}], "weekdayDescriptions": ["Monday: 10:30\u202fAM\u2009\u2013\u20097:00\u202fPM", "Tuesday: 10:30\u202fAM\u2009\u2013\u20097:00\u202fPM", "Wednesday: 10:30\u202fAM\u2009\u2013\u20097:00\u202fPM", "Thursday: 10:30\u202fAM\u2009\u2013\u20097:00\u202fPM", "Friday: 10:30\u202fAM\u2009\u2013\u20097:00\u202fPM", "Saturday: Closed", "Sunday: Closed"], "nextOpenTime": "2026-02-09T16:30:00Z"}, "businessStatus": "OPERATIONAL", "userRatingCount": 54, "displayName": {"text": "Blue Bamboo Chinese restaurant", "languageCode": "en"}, "takeout": true, "dineIn": true}, {"id": "ChIJd0qzroYhTIYR-yuxvmjYX4k", "nationalPhoneNumber": "(469) 206-3510", "formattedAddress": "6160 Belt Line Rd, Dallas, TX 75254, USA", "addressComponents": [{"longText": "6160", "shortText": "6160", "types": ["street_number"], "languageCode": "en-US"}, {"longText": "Belt Line Road", "shortText": "Belt Line Rd", "types": ["route"], "languageCode": "en"}, {"longText": "Far North Dallas", "shortText": "Far North Dallas", "types": ["neighborhood", "political"], "languageCode": "en"}, {"longText": "Dallas", "shortText": "Dallas", "types": ["locality", "political"], "languageCode": "en"}, {"longText": "Dallas County", "shortText": "Dallas County", "types": ["administrative_area_level_2", "political"], "languageCode": "en"}, {"longText": "Texas", "shortText": "TX", "types": ["administrative_area_level_1", "political"], "languageCode": "en"}, {"longText": "United States", "shortText": "US", "types": ["country", "political"], "languageCode": "en"}, {"longText": "75254", "shortText": "75254", "types": ["postal_code"], "languageCode": "en-US"}], "location": {"latitude": 32.950774200000005, "longitude": -96.8001658}, "rating": 3.3, "googleMapsUri": "https://maps.google.com/?cid=9898868450371120123&g_mp=Cilnb29nbGUubWFwcy5wbGFjZXMudjEuUGxhY2VzLlNlYXJjaE5lYXJieRACGAQgAA", "websiteUri": "http://weitastyasian.com/", "regularOpeningHours": {"openNow": true, "periods": [{"open": {"day": 0, "hour": 11, "minute": 0}, "close": {"day": 0, "hour": 22, "minute": 0}}, {"open": {"day": 1, "hour": 11, "minute": 0}, "close": {"day": 1, "hour": 22, "minute": 0}}, {"open": {"day": 2, "hour": 11, "minute": 0}, "close": {"day": 2, "hour": 22, "minute": 0}}, {"open": {"day": 3, "hour": 11, "minute": 0}, "close": {"day": 3, "hour": 22, "minute": 0}}, {"open": {"day": 4, "hour": 11, "minute": 0}, "close": {"day": 4, "hour": 22, "minute": 0}}, {"open": {"day": 5, "hour": 11, "minute": 0}, "close": {"day": 5, "hour": 22, "minute": 0}}, {"open": {"day": 6, "hour": 11, "minute": 0}, "close": {"day": 6, "hour": 22, "minute": 0}}], "weekdayDescriptions": ["Monday: 11:00\u202fAM\u2009\u2013\u200910:00\u202fPM", "Tuesday: 11:00\u202fAM\u2009\u2013\u200910:00\u202fPM", "Wednesday: 11:00\u202fAM\u2009\u2013\u200910:00\u202fPM", "Thursday: 11:00\u202fAM\u2009\u2013\u200910:00\u202fPM", "Friday: 11:00\u202fAM\u2009\u2013\u200910:00\u202fPM", "Saturday: 11:00\u202fAM\u2009\u2013\u200910:00\u202fPM", "Sunday: 11:00\u202fAM\u2009\u2013\u200910:00\u202fPM"], "nextCloseTime": "2026-02-08T04:00:00Z"}, "businessStatus": "OPERATIONAL", "userRatingCount": 229, "displayName": {"text": "Wei Tasty Asian", "languageCode": "en"}, "takeout": true, "delivery": true, "dineIn": true}]}