{"cached_at": "2026-02-08T03:23:19.774682+00:00", "request": {"lat": 42.39896756756757, "lng": -83.22859731354482, "radius": 5000}, "response": [{"id": "ChIJX5MuS8e1JIgRyqSiZkFUcG8", "nationalPhoneNumber": "(313) 532-2828", "formattedAddress": "16921 Telegraph Rd, Detroit, MI 48219, USA", "addressComponents": [{"longText": "16921", "shortText": "16921", "types": ["street_number"], "languageCode": "en-US"}, {"longText": "Telegraph Road", "shortText": "Telegraph Rd", "types": ["route"], "languageCode": "en"}, {"longText": "South Of Six", "shortText": "South Of Six", "types": ["neighborhood", "political"], "languageCode": "en"}, {"longText": "Detroit", "shortText": "Detroit", "types": ["locality", "political"], "languageCode": "en"}, {"longText": "Wayne County", "shortText": "Wayne County", "types": ["administrative_area_level_2", "political"], "languageCode": "en"}, {"longText": "Michigan", "shortText": "MI", "types": ["administrative_area_level_1", "political"], "languageCode": "en"}, {"longText": "United States", "shortText": "US", "types": ["country", "political"], "languageCode": "en"}, {"longText": "48219", "shortText": "48219", "types": ["postal_code"], "languageCode": "en-US"}], "location": {"latitude": 42.4136978, "longitude": -83.27764979999999}, "rating": 4.2, "googleMapsUri": "https://maps.google.com/?cid=8030010775473136842&g_mp=Cilnb29nbGUubWFwcy5wbGFjZXMudjEuUGxhY2VzLlNlYXJjaE5lYXJieRACGAQgAA", "websiteUri": "https://www.sunchina2022.com/", "regularOpeningHours": {"openNow": false, "periods": [{"open": {"day": 0, "hour": 14, "minute": 0}, "close": {"day": 0, "hour": 22, "minute": 0}}, {"open": {"day": 2, "hour": 14, "minute": 0}, "close": {"day": 2, "hour": 22, "minute": 0}}, {"open": {"day": 3, "hour": 14, "minute": 0}, "close": {"day": 3, "hour": 22, "minute": 0}}, {"open": {"day": 5, "hour": 14, "minute": 0}, "close": {"day": 5, "hour": 22, "minute": 0}}, {"open": {"day": 6, "hour": 14, "minute": 0}, "close": {"day": 6, "hour": 22, "minute": 0}}], "weekdayDescriptions": ["Monday: Closed", "Tuesday: 2:00\u2009\u2013\u200910:00\u202fPM", "Wednesday: 2:00\u2009\u2013\u200910:00\u202fPM", "Thursday: Closed", "Friday: 2:00\u2009\u2013\u200910:00\u202fPM", "Saturday: 2:00\u2009\u2013\u200910:00\u202fPM", "Sunday: 2:00\u2009\u2013\u200910:00\u202fPM"], "nextOpenTime": "2026-02-08T19:00:00Z"}, "businessStatus": "OPERATIONAL", "priceLevel": "PRICE_LEVEL_MODERATE", "userRatingCount": 1731, "displayName": {"text": "Sun China", "languageCode": "en"}, "takeout": true, "delivery": false, "dineIn": true}, {"id": "ChIJ-YhRie_LJIgRCPXKzPjkd3I", "nationalPhoneNumber": "(313) 341-1700", "formattedAddress": "13337 W McNichols Rd, Detroit, MI 48235, USA", "addressComponents": [{"longText": "13337", "shortText": "13337", "types": ["street_number"], "languageCode": "en-US"}, {"longText": "West McNichols Road", "shortText": "W McNichols Rd", "types": ["route"], "languageCode": "en"}, {"longText": "Harmony Village", "shortText": "Harmony Village", "types": ["neighborhood", "political"], "languageCode": "en"}, {"longText": "Detroit", "shortText": "Detroit", "types": ["locality", "political"], "languageCode": "en"}, {"longText": "Wayne County", "shortText": "Wayne County", "types": ["administrative_area_level_2", "political"], "languageCode": "en"}, {"longText": "Michigan", "shortText": "MI", "types": ["administrative_area_level_1", "political"], "languageCode": "en"}, {"longText": "United States", "shortText": "US", "types": ["country", "political"], "languageCode": "en"}, {"longText": "48235", "shortText": "48235", "types": ["postal_code"], "languageCode": "en-US"}], "location": {"latitude": 42.4163655, "longitude": -83.1773231}, "rating": 4.1, "googleMapsUri": "https://maps.google.com/?cid=8248312999791228168&g_mp=Cilnb29nbGUubWFwcy5wbGFjZXMudjEuUGxhY2VzLlNlYXJjaE5lYXJieRACGAQgAA", "websiteUri": "http://www.goldenbowlchopsueymi.com/", "businessStatus": "CLOSED_TEMPORARILY", "priceLevel": "PRICE_LEVEL_INEXPENSIVE", "userRatingCount": 855, "displayName": {"text": "Golden Bowl Chop Suey", "languageCode": "en"}, "takeout": true, "delivery": true}, {"id": "ChIJaz62s_W1JIgRlKuz8TyiJWg", "nationalPhoneNumber": "(313) 532-9966", "formattedAddress": "21427 Grand River Ave, Detroit, MI 48219, USA", "addressComponents": [{"longText": "21427", "shortText": "21427", "types": ["street_number"], "languageCode": "en-US"}, {"longText": "Grand River Avenue", "shortText": "Grand River Ave", "types": ["route"], "languageCode": "en"}, {"longText": "Miller Grove", "shortText": "Miller Grove", "types": ["neighborhood", "political"], "languageCode": "en"}, {"longText": "Detroit", "shortText": "Detroit", "types": ["locality", "political"], "languageCode": "en"}, {"longText": "Wayne County", "shortText": "Wayne County", "types": ["administrative_area_level_2", "political"], "languageCode": "en"}, {"longText": "Michigan", "shortText": "MI", "types": ["administrative_area_level_1", "political"], "languageCode": "en"}, {"longText": "United States", "shortText": "US", "types": ["country", "political"], "languageCode": "en"}, {"longText": "48219", "shortText": "48219", "types": ["postal_code"], "languageCode": "en-US"}, {"longText": "3801", "shortText": "3801", "types": ["postal_code_suffix"], "languageCode": "en-US"}], "location": {"latitude": 42.414459699999995, "longitude": -83.2534161}, "rating": 3.6, "googleMapsUri": "https://maps.google.com/?cid=7504582736719621012&g_mp=Cilnb29nbGUubWFwcy5wbGFjZXMudjEuUGxhY2VzLlNlYXJjaE5lYXJieRACGAQgAA", "regularOpeningHours": {"openNow": false, "periods": [{"open": {"day": 1, "hour": 11, "minute": 0}, "close": {"day": 1, "hour": 21, "minute": 30}}, {"open": {"day": 2, "hour": 11, "minute": 0}, "close": {"day": 2, "hour": 21, "minute": 30}}, {"open": {"day": 3, "hour": 11, "minute": 0}, "close": {"day": 3, "hour": 21, "minute": 30}}, {"open": {"day": 4, "hour": 11, "minute": 0}, "close": {"day": 4, "hour": 21, "minute": 30}}, {"open": {"day": 5, "hour": 11, "minute": 0}, "close": {"day": 5, "hour": 21, "minute": 30}}, {"open": {"day": 6, "hour": 11, "minute": 0}, "close": {"day": 6, "hour": 21, "minute": 30}}], "weekdayDescriptions": ["Monday: 11:00\u202fAM\u2009\u2013\u20099:30\u202fPM", "Tuesday: 11:00\u202fAM\u2009\u2013\u20099:30\u202fPM", "Wednesday: 11:00\u202fAM\u2009\u2013\u20099:30\u202fPM", "Thursday: 11:00\u202fAM\u2009\u2013\u20099:30\u202fPM", "Friday: 11:00\u202fAM\u2009\u2013\u20099:30\u202fPM", "Saturday: 11:00\u202fAM\u2009\u2013\u20099:30\u202fPM", "Sunday: Closed"], "nextOpenTime": "2026-02-09T16:00:00Z"}, "businessStatus": "OPERATIONAL", "priceLevel": "PRICE_LEVEL_INEXPENSIVE", "userRatingCount": 236, "displayName": {"text": "China House", "languageCode": "en"}, "takeout": true, "delivery": true}, {"id": "ChIJ-y2slKjLJIgRjEiTzpvMGjQ", "nationalPhoneNumber": "(313) 837-8888", "formattedAddress": "14307 Greenfield Rd, Detroit, MI 48227, USA", "addressComponents": [{"longText": "14307", "shortText": "14307", "types": ["street_number"], "languageCode": "en-US"}, {"longText": "Greenfield Road", "shortText": "Greenfield Rd", "types": ["route"], "languageCode": "en"}, {"longText": "Greenfield-Grand River", "shortText": "Greenfield-Grand River", "types": ["neighborhood", "political"], "languageCode": "en"}, {"longText": "Detroit", "shortText": "Detroit", "types": ["locality", "political"], "languageCode": "en"}, {"longText": "Wayne County", "shortText": "Wayne County", "types": ["administrative_area_level_2", "political"], "languageCode": "en"}, {"longText": "Michigan", "shortText": "MI", "types": ["administrative_area_level_1", "political"], "languageCode": "en"}, {"longText": "United States", "shortText": "US", "types": ["country", "political"], "languageCode": "en"}, {"longText": "48227", "shortText": "48227", "types": ["postal_code"], "languageCode": "en-US"}, {"longText": "2107", "shortText": "2107", "types": ["postal_code_suffix"], "languageCode": "en-US"}], "location": {"latitude": 42.3920628, "longitude": -83.1989256}, "rating": 3.7, "googleMapsUri": "https://maps.google.com/?cid=3754538208924485772&g_mp=Cilnb29nbGUubWFwcy5wbGFjZXMudjEuUGxhY2VzLlNlYXJjaE5lYXJieRACGAQgAA", "websiteUri": "http://greatwalldetroit.weebly.com/", "regularOpeningHours": {"openNow": true, "periods": [{"open": {"day": 0, "hour": 13, "minute": 0}, "close": {"day": 0, "hour": 22, "minute": 0}}, {"open": {"day": 1, "hour": 12, "minute": 0}, "close": {"day": 1, "hour": 22, "minute": 0}}, {"open": {"day": 3, "hour": 12, "minute": 0}, "close": {"day": 3, "hour": 22, "minute": 0}}, {"open": {"day": 4, "hour": 12, "minute": 0}, "close": {"day": 4, "hour": 22, "minute": 0}}, {"open": {"day": 5, "hour": 12, "minute": 0}, "close": {"day": 5, "hour": 23, "minute": 0}}, {"open": {"day": 6, "hour": 12, "minute": 0}, "close": {"day": 6, "hour": 23, "minute": 0}}], "weekdayDescriptions": ["Monday: 12:00\u2009\u2013\u200910:00\u202fPM", "Tuesday: Closed", "Wednesday: 12:00\u2009\u2013\u200910:00\u202fPM", "Thursday: 12:00\u2009\u2013\u200910:00\u202fPM", "Friday: 12:00\u2009\u2013\u200911:00\u202fPM", "Saturday: 12:00\u2009\u2013\u200911:00\u202fPM", "Sunday: 1:00\u2009\u2013\u200910:00\u202fPM"], "nextCloseTime": "2026-02-08T04:00:00Z"}, "businessStatus": "OPERATIONAL", "priceLevel": "PRICE_LEVEL_INEXPENSIVE", "userRatingCount": 260, "displayName": {"text": "Great Wall", "languageCode": "en"}, "takeout": true, "delivery": false}, {"id": "ChIJiTAwXEPKJIgRwAi1HPniYng", "nationalPhoneNumber": "(313) 837-3771", "formattedAddress": "18614 Fenkell Ave, Detroit, MI 48223, USA", "addressComponents": [{"longText": "18614", "shortText": "18614", "types": ["street_number"], "languageCode": "en-US"}, {"longText": "Fenkell Avenue", "shortText": "Fenkell Ave", "types": ["route"], "languageCode": "en"}, {"longText": "Rosedale Park Historic District", "shortText": "Rosedale Park Historic District", "types": ["neighborhood", "political"], "languageCode": "en"}, {"longText": "Detroit", "shortText": "Detroit", "types": ["locality", "political"], "languageCode": "en"}, {"longText": "Wayne County", "shortText": "Wayne County", "types": ["administrative_area_level_2", "political"], "languageCode": "en"}, {"longText": "Michigan", "shortText": "MI", "types": ["administrative_area_level_1", "political"], "languageCode": "en"}, {"longText": "United States", "shortText": "US", "types": ["country", "political"], "languageCode": "en"}, {"longText": "48223", "shortText": "48223", "types": ["postal_code"], "languageCode": "en-US"}, {"longText": "2315", "shortText": "2315", "types": ["postal_code_suffix"], "languageCode": "en-US"}], "location": {"latitude": 42.4021626, "longitude": -83.2241938}, "rating": 4.1, "googleMapsUri": "https://maps.google.com/?cid=8674745391825356992&g_mp=Cilnb29nbGUubWFwcy5wbGFjZXMudjEuUGxhY2VzLlNlYXJjaE5lYXJieRACGAQgAA", "businessStatus": "CLOSED_TEMPORARILY", "priceLevel": "PRICE_LEVEL_INEXPENSIVE", "userRatingCount": 458, "displayName": {"text": "Panda Chinese Restaurant", "languageCode": "en"}, "takeout": true}, {"id": "ChIJ57UCFDrKJIgR_pfWYgEw0O4", "nationalPhoneNumber": "(313) 535-5300", "formattedAddress": "18205 W McNichols Rd, Detroit, MI 48219, USA", "addressComponents": [{"longText": "18205", "shortText": "18205", "types": ["street_number"], "languageCode": "en-US"}, {"longText": "West McNichols Road", "shortText": "W McNichols Rd", "types": ["route"], "languageCode": "en"}, {"longText": "North Rosedale Park", "shortText": "North Rosedale Park", "types": ["neighborhood", "political"], "languageCode": "en"}, {"longText": "Detroit", "shortText": "Detroit", "types": ["locality", "political"], "languageCode": "en"}, {"longText": "Wayne County", "shortText": "Wayne County", "types": ["administrative_area_level_2", "political"], "languageCode": "en"}, {"longText": "Michigan", "shortText": "MI", "types": ["administrative_area_level_1", "political"], "languageCode": "en"}, {"longText": "United States", "shortText": "US", "types": ["country", "political"], "languageCode": "en"}, {"longText": "48219", "shortText": "48219", "types": ["postal_code"], "languageCode": "en-US"}], "location": {"latitude": 42.415272300000005, "longitude": -83.22030319999999}, "rating": 3.9, "googleMapsUri": "https://maps.google.com/?cid=17208306958693996542&g_mp=Cilnb29nbGUubWFwcy5wbGFjZXMudjEuUGxhY2VzLlNlYXJjaE5lYXJieRACGAQgAA", "websiteUri": "https://chengsgardendetroit.weebly.com/", "regularOpeningHours": {"openNow": false, "periods": [{"open": {"day": 0, "hour": 13, "minute": 30}, "close": {"day": 0, "hour": 21, "minute": 0}}, {"open": {"day": 2, "hour": 12, "minute": 0}, "close": {"day": 2, "hour": 21, "minute": 0}}, {"open": {"day": 3, "hour": 12, "minute": 0}, "close": {"day": 3, "hour": 21, "minute": 0}}, {"open": {"day": 4, "hour": 12, "minute": 0}, "close": {"day": 4, "hour": 21, "minute": 0}}, {"open": {"day": 5, "hour": 12, "minute": 0}, "close": {"day": 5, "hour": 21, "minute": 0}}, {"open": {"day": 6, "hour": 12, "minute": 0}, "close": {"day": 6, "hour": 21, "minute": 0}}], "weekdayDescriptions": ["Monday: Closed", "Tuesday: 12:00\u2009\u2013\u20099:00\u202fPM", "Wednesday: 12:00\u2009\u2013\u20099:00\u202fPM", "Thursday: 12:00\u2009\u2013\u20099:00\u202fPM", "Friday: 12:00\u2009\u2013\u20099:00\u202fPM", "Saturday: 12:00\u2009\u2013\u20099:00\u202fPM", "Sunday: 1:30\u2009\u2013\u20099:00\u202fPM"], "nextOpenTime": "2026-02-08T18:30:00Z"}, "businessStatus": "OPERATIONAL", "priceLevel": "PRICE_LEVEL_INEXPENSIVE", "userRatingCount": 161, "displayName": {"text": "Cheng's Garden Restaurant", "languageCode": "en"}, "takeout": true}, {"id": "ChIJtURpsALKJIgRcxTN9WLgKRw", "nationalPhoneNumber": "(313) 538-3333", "formattedAddress": "20160 W Seven Mile Rd, Detroit, MI 48219, USA", "addressComponents": [{"longText": "20160", "shortText": "20160", "types": ["street_number"], "languageCode": "en-US"}, {"longText": "West Seven Mile Road", "shortText": "W Seven Mile Rd", "types": ["route"], "languageCode": "en"}, {"longText": "Evergreen Lahser 7/8", "shortText": "Evergreen Lahser 7/8", "types": ["neighborhood", "political"], "languageCode": "en"}, {"longText": "Detroit", "shortText": "Detroit", "types": ["locality", "political"], "languageCode": "en"}, {"longText": "Wayne County", "shortText": "Wayne County", "types": ["administrative_area_level_2", "political"], "languageCode": "en"}, {"longText": "Michigan", "shortText": "MI", "types": ["administrative_area_level_1", "political"], "languageCode": "en"}, {"longText": "United States", "shortText": "US", "types": ["country", "political"], "languageCode": "en"}, {"longText": "48219", "shortText": "48219", "types": ["postal_code"], "languageCode": "en-US"}, {"longText": "3472", "shortText": "3472", "types": ["postal_code_suffix"], "languageCode": "en-US"}], "location": {"latitude": 42.4299399, "longitude": -83.2404329}, "rating": 3.5, "googleMapsUri": "https://maps.google.com/?cid=2029399822742393971&g_mp=Cilnb29nbGUubWFwcy5wbGFjZXMudjEuUGxhY2VzLlNlYXJjaE5lYXJieRACGAQgAA", "websiteUri": "http://www.chinaoneevergreenmi.com/", "regularOpeningHours": {"openNow": true, "periods": [{"open": {"day": 1, "hour": 11, "minute": 0}, "close": {"day": 1, "hour": 22, "minute": 0}}, {"open": {"day": 2, "hour": 11, "minute": 0}, "close": {"day": 2, "hour": 22, "minute": 0}}, {"open": {"day": 3, "hour": 11, "minute": 0}, "close": {"day": 3, "hour": 22, "minute": 0}}, {"open": {"day": 4, "hour": 11, "minute": 0}, "close": {"day": 4, "hour": 22, "minute": 0}}, {"open": {"day": 5, "hour": 11, "minute": 0}, "close": {"day": 5, "hour": 22, "minute": 30}}, {"open": {"day": 6, "hour": 11, "minute": 0}, "close": {"day": 6, "hour": 22, "minute": 30}}], "weekdayDescriptions": ["Monday: 11:00\u202fAM\u2009\u2013\u200910:00\u202fPM", "Tuesday: 11:00\u202fAM\u2009\u2013\u200910:00\u202fPM", "Wednesday: 11:00\u202fAM\u2009\u2013\u200910:00\u202fPM", "Thursday: 11:00\u202fAM\u2009\u2013\u200910:00\u202fPM", "Friday: 11:00\u202fAM\u2009\u2013\u200910:30\u202fPM", "Saturday: 11:00\u202fAM\u2009\u2013\u200910:30\u202fPM", "Sunday: Closed"], "nextCloseTime": "2026-02-08T03:30:00Z"}, "businessStatus": "OPERATIONAL", "priceLevel": "PRICE_LEVEL_INEXPENSIVE", "userRatingCount": 156, "displayName": {"text": "China One Evergreen", "languageCode": "en"}, "takeout": true, "delivery": true, "dineIn": true}, {"id": "ChIJS1BvQKjLJIgRQAOw8Et_7N4", "nationalPhoneNumber": "(313) 836-6000", "formattedAddress": "14135 Greenfield Rd, Detroit, MI 48227, USA", "addressComponents": [{"longText": "14135", "shortText": "14135", "types": ["street_number"], "languageCode": "en-US"}, {"longText": "Greenfield Road", "shortText": "Greenfield Rd", "types": ["route"], "languageCode": "en"}, {"longText": "Greenfield-Grand River", "shortText": "Greenfield-Grand River", "types": ["neighborhood", "political"], "languageCode": "en"}, {"longText": "Detroit", "shortText": "Detroit", "types": ["locality", "political"], "languageCode": "en"}, {"longText": "Wayne County", "shortText": "Wayne County", "types": ["administrative_area_level_2", "political"], "languageCode": "en"}, {"longText": "Michigan", "shortText": "MI", "types": ["administrative_area_level_1", "political"], "languageCode": "en"}, {"longText": "United States", "shortText": "US", "types": ["country", "political"], "languageCode": "en"}, {"longText": "48227", "shortText": "48227", "types": ["postal_code"], "languageCode": "en-US"}, {"longText": "2191", "shortText": "2191", "types": ["postal_code_suffix"], "languageCode": "en-US"}], "location": {"latitude": 42.3898997, "longitude": -83.1986191}, "rating": 4, "googleMapsUri": "https://maps.google.com/?cid=16063353935061058368&g_mp=Cilnb29nbGUubWFwcy5wbGFjZXMudjEuUGxhY2VzLlNlYXJjaE5lYXJieRACGAQgAA", "businessStatus": "CLOSED_TEMPORARILY", "priceLevel": "PRICE_LEVEL_INEXPENSIVE", "userRatingCount": 231, "displayName": {"text": "Rikshaw House", "languageCode": "en"}, "takeout": true}]}