{"cached_at": "2026-02-08T03:25:44.124321+00:00", "request": {"lat": 43.1566, "lng": -77.51617659102466, "radius": 5000}, "response": [{"id": "ChIJyXGxmom11okRzggPRqd3km8", "nationalPhoneNumber": "(585) 482-0210", "formattedAddress": "1014 Culver Rd, Rochester, NY 14609, USA", "addressComponents": [{"longText": "1014", "shortText": "1014", "types": ["street_number"], "languageCode": "en-US"}, {"longText": "Culver Road", "shortText": "Culver Rd", "types": ["route"], "languageCode": "en"}, {"longText": "North Winton Village", "shortText": "North Winton Village", "types": ["neighborhood", "political"], "languageCode": "en"}, {"longText": "Rochester", "shortText": "Rochester", "types": ["locality", "political"], "languageCode": "en"}, {"longText": "Monroe County", "shortText": "Monroe County", "types": ["administrative_area_level_2", "political"], "languageCode": "en"}, {"longText": "New York", "shortText": "NY", "types": ["administrative_area_level_1", "political"], "languageCode": "en"}, {"longText": "United States", "shortText": "US", "types": ["country", "political"], "languageCode": "en"}, {"longText": "14609", "shortText": "14609", "types": ["postal_code"], "languageCode": "en-US"}], "location": {"latitude": 43.16354520000001, "longitude": -77.5639393}, "rating": 4.5, "googleMapsUri": "https://maps.google.com/?cid=8039619845128390862&g_mp=Cilnb29nbGUubWFwcy5wbGFjZXMudjEuUGxhY2VzLlNlYXJjaE5lYXJieRACGAQgAA", "websiteUri": "https://changlungrestaurant.com/", "regularOpeningHours": {"openNow": false, "periods": [{"open": {"day": 0, "hour": 0, "minute": 0}, "close": {"day": 0, "hour": 21, "minute": 45}}, {"open": {"day": 1, "hour": 11, "minute": 0}, "close": {"day": 1, "hour": 21, "minute": 45}}, {"open": {"day": 2, "hour": 11, "minute": 0}, "close": {"day": 2, "hour": 21, "minute": 45}}, {"open": {"day": 3, "hour": 11, "minute": 0}, "close": {"day": 3, "hour": 21, "minute": 45}}, {"open": {"day": 4, "hour": 11, "minute": 0}, "close": {"day": 4, "hour": 21, "minute": 45}}, {"open": {"day": 5, "hour": 11, "minute": 0}, "close": {"day": 5, "hour": 22, "minute": 15}}, {"open": {"day": 6, "hour": 11, "minute": 0}, "close": {"day": 6, "hour": 22, "minute": 15}}], "weekdayDescriptions": ["Monday: 11:00\u202fAM\u2009\u2013\u20099:45\u202fPM", "Tuesday: 11:00\u202fAM\u2009\u2013\u20099:45\u202fPM", "Wednesday: 11:00\u202fAM\u2009\u2013\u20099:45\u202fPM", "Thursday: 11:00\u202fAM\u2009\u2013\u20099:45\u202fPM", "Friday: 11:00\u202fAM\u2009\u2013\u200910:15\u202fPM", "Saturday: 11:00\u202fAM\u2009\u2013\u200910:15\u202fPM", "Sunday: 12:00\u202fAM\u2009\u2013\u20099:45\u202fPM"], "nextOpenTime": "2026-02-08T05:00:00Z"}, "businessStatus": "OPERATIONAL", "priceLevel": "PRICE_LEVEL_INEXPENSIVE", "userRatingCount": 491, "displayName": {"text": "Chang Lung chinese restaurant", "languageCode": "en"}, "takeout": true, "delivery": false, "dineIn": true}, {"id": "ChIJ561gzGTL1okR55xYIoh3DXk", "nationalPhoneNumber": "(585) 385-2808", "formattedAddress": "1802 Penfield Rd, Penfield, NY 14526, USA", "addressComponents": [{"longText": "1802", "shortText": "1802", "types": ["street_number"], "languageCode": "en-US"}, {"longText": "Penfield Road", "shortText": "Penfield Rd", "types": ["route"], "languageCode": "en"}, {"longText": "Penfield", "shortText": "Penfield", "types": ["locality", "political"], "languageCode": "en"}, {"longText": "Penfield", "shortText": "Penfield", "types": ["administrative_area_level_3", "political"], "languageCode": "en"}, {"longText": "Monroe County", "shortText": "Monroe County", "types": ["administrative_area_level_2", "political"], "languageCode": "en"}, {"longText": "New York", "shortText": "NY", "types": ["administrative_area_level_1", "political"], "languageCode": "en"}, {"longText": "United States", "shortText": "US", "types": ["country", "political"], "languageCode": "en"}, {"longText": "14526", "shortText": "14526", "types": ["postal_code"], "languageCode": "en-US"}], "location": {"latitude": 43.1306193, "longitude": -77.4776419}, "rating": 4.3, "googleMapsUri": "https://maps.google.com/?cid=8722759479862009063&g_mp=Cilnb29nbGUubWFwcy5wbGFjZXMudjEuUGxhY2VzLlNlYXJjaE5lYXJieRACGAQgAA", "websiteUri": "http://www.hongwahrestaurant.com/", "regularOpeningHours": {"openNow": false, "periods": [{"open": {"day": 0, "hour": 11, "minute": 30}, "close": {"day": 0, "hour": 21, "minute": 0}}, {"open": {"day": 1, "hour": 11, "minute": 0}, "close": {"day": 1, "hour": 21, "minute": 0}}, {"open": {"day": 2, "hour": 11, "minute": 0}, "close": {"day": 2, "hour": 21, "minute": 0}}, {"open": {"day": 3, "hour": 11, "minute": 0}, "close": {"day": 3, "hour": 21, "minute": 0}}, {"open": {"day": 4, "hour": 11, "minute": 0}, "close": {"day": 4, "hour": 21, "minute": 0}}, {"open": {"day": 5, "hour": 11, "minute": 0}, "close": {"day": 5, "hour": 21, "minute": 30}}, {"open": {"day": 6, "hour": 11, "minute": 0}, "close": {"day": 6, "hour": 21, "minute": 30}}], "weekdayDescriptions": ["Monday: 11:00\u202fAM\u2009\u2013\u20099:00\u202fPM", "Tuesday: 11:00\u202fAM\u2009\u2013\u20099:00\u202fPM", "Wednesday: 11:00\u202fAM\u2009\u2013\u20099:00\u202fPM", "Thursday: 11:00\u202fAM\u2009\u2013\u20099:00\u202fPM", "Friday: 11:00\u202fAM\u2009\u2013\u20099:30\u202fPM", "Saturday: 11:00\u202fAM\u2009\u2013\u20099:30\u202fPM", "Sunday: 11:30\u202fAM\u2009\u2013\u20099:00\u202fPM"], "nextOpenTime": "2026-02-08T16:30:00Z"}, "businessStatus": "OPERATIONAL", "priceLevel": "PRICE_LEVEL_INEXPENSIVE", "userRatingCount": 934, "displayName": {"text": "Hong Wah Restaurant", "languageCode": "en"}, "takeout": true, "dineIn": true}, {"id": "ChIJ3QwEy4bK1okR7NGUgwmoAAI", "nationalPhoneNumber": "(585) 256-1010", "formattedAddress": "1801 East Ave, Rochester, NY 14610, USA", "addressComponents": [{"longText": "1801", "shortText": "1801", "types": ["street_number"], "languageCode": "en-US"}, {"longText": "East Avenue", "shortText": "East Ave", "types": ["route"], "languageCode": "en"}, {"longText": "East Avenue", "shortText": "East Avenue", "types": ["neighborhood", "political"], "languageCode": "en"}, {"longText": "Rochester", "shortText": "Rochester", "types": ["locality", "political"], "languageCode": "en"}, {"longText": "Monroe County", "shortText": "Monroe County", "types": ["administrative_area_level_2", "political"], "languageCode": "en"}, {"longText": "New York", "shortText": "NY", "types": ["administrative_area_level_1", "political"], "languageCode": "en"}, {"longText": "United States", "shortText": "US", "types": ["country", "political"], "languageCode": "en"}, {"longText": "14610", "shortText": "14610", "types": ["postal_code"], "languageCode": "en-US"}], "location": {"latitude": 43.1451485, "longitude": -77.5562449}, "rating": 4.6, "googleMapsUri": "https://maps.google.com/?cid=144299946891596268&g_mp=Cilnb29nbGUubWFwcy5wbGFjZXMudjEuUGxhY2VzLlNlYXJjaE5lYXJieRACGAQgAA", "websiteUri": "https://www.eastavewongs.com/", "regularOpeningHours": {"openNow": false, "periods": [{"open": {"day": 0, "hour": 10, "minute": 30}, "close": {"day": 0, "hour": 21, "minute": 30}}, {"open": {"day": 2, "hour": 10, "minute": 30}, "close": {"day": 2, "hour": 21, "minute": 30}}, {"open": {"day": 3, "hour": 10, "minute": 30}, "close": {"day": 3, "hour": 21, "minute": 30}}, {"open": {"day": 4, "hour": 10, "minute": 30}, "close": {"day": 4, "hour": 21, "minute": 30}}, {"open": {"day": 5, "hour": 10, "minute": 30}, "close": {"day": 5, "hour": 21, "minute": 30}}, {"open": {"day": 6, "hour": 10, "minute": 30}, "close": {"day": 6, "hour": 21, "minute": 30}}], "weekdayDescriptions": ["Monday: Closed", "Tuesday: 10:30\u202fAM\u2009\u2013\u20099:30\u202fPM", "Wednesday: 10:30\u202fAM\u2009\u2013\u20099:30\u202fPM", "Thursday: 10:30\u202fAM\u2009\u2013\u20099:30\u202fPM", "Friday: 10:30\u202fAM\u2009\u2013\u20099:30\u202fPM", "Saturday: 10:30\u202fAM\u2009\u2013\u20099:30\u202fPM", "Sunday: 10:30\u202fAM\u2009\u2013\u20099:30\u202fPM"], "nextOpenTime": "2026-02-08T15:30:00Z"}, "businessStatus": "OPERATIONAL", "priceLevel": "PRICE_LEVEL_INEXPENSIVE", "userRatingCount": 339, "displayName": {"text": "Wong's Kitchen Rochester", "languageCode": "en"}, "takeout": true, "dineIn": true}, {"id": "ChIJxX_7G33K1okRXCFndDqVYV4", "nationalPhoneNumber": "(585) 482-0870", "formattedAddress": "268 Winton Rd N, Rochester, NY 14610, USA", "addressComponents": [{"longText": "268", "shortText": "268", "types": ["street_number"], "languageCode": "en-US"}, {"longText": "Winton Road North", "shortText": "Winton Rd N", "types": ["route"], "languageCode": "en"}, {"longText": "Browncroft", "shortText": "Browncroft", "types": ["neighborhood", "political"], "languageCode": "en"}, {"longText": "Rochester", "shortText": "Rochester", "types": ["locality", "political"], "languageCode": "en"}, {"longText": "Monroe County", "shortText": "Monroe County", "types": ["administrative_area_level_2", "political"], "languageCode": "en"}, {"longText": "New York", "shortText": "NY", "types": ["administrative_area_level_1", "political"], "languageCode": "en"}, {"longText": "United States", "shortText": "US", "types": ["country", "political"], "languageCode": "en"}, {"longText": "14610", "shortText": "14610", "types": ["postal_code"], "languageCode": "en-US"}, {"longText": "1238", "shortText": "1238", "types": ["postal_code_suffix"], "languageCode": "en-US"}], "location": {"latitude": 43.150639299999995, "longitude": -77.5521668}, "rating": 4.4, "googleMapsUri": "https://maps.google.com/?cid=6800880990599717212&g_mp=Cilnb29nbGUubWFwcy5wbGFjZXMudjEuUGxhY2VzLlNlYXJjaE5lYXJieRACGAQgAA", "websiteUri": "https://smorefood.com/order-online/china-garden-kitchen-rochester-14610-eb66ktik?utm_source=gmb&utm_medium=website", "regularOpeningHours": {"openNow": true, "periods": [{"open": {"day": 0, "hour": 12, "minute": 0}, "close": {"day": 0, "hour": 21, "minute": 0}}, {"open": {"day": 1, "hour": 11, "minute": 0}, "close": {"day": 1, "hour": 21, "minute": 30}}, {"open": {"day": 3, "hour": 11, "minute": 0}, "close": {"day": 3, "hour": 21, "minute": 30}}, {"open": {"day": 4, "hour": 12, "minute": 0}, "close": {"day": 4, "hour": 21, "minute": 30}}, {"open": {"day": 5, "hour": 11, "minute": 0}, "close": {"day": 5, "hour": 22, "minute": 30}}, {"open": {"day": 6, "hour": 11, "minute": 0}, "close": {"day": 6, "hour": 22, "minute": 30}}], "weekdayDescriptions": ["Monday: 11:00\u202fAM\u2009\u2013\u20099:30\u202fPM", "Tuesday: Closed", "Wednesday: 11:00\u202fAM\u2009\u2013\u20099:30\u202fPM", "Thursday: 12:00\u2009\u2013\u20099:30\u202fPM", "Friday: 11:00\u202fAM\u2009\u2013\u200910:30\u202fPM", "Saturday: 11:00\u202fAM\u2009\u2013\u200910:30\u202fPM", "Sunday: 12:00\u2009\u2013\u20099:00\u202fPM"], "nextCloseTime": "2026-02-08T03:30:00Z"}, "businessStatus": "OPERATIONAL", "priceLevel": "PRICE_LEVEL_INEXPENSIVE", "userRatingCount": 353, "displayName": {"text": "China Garden Kitchen", "languageCode": "en"}, "takeout": true, "delivery": true, "dineIn": true}, {"id": "ChIJXTy2AmbJ1okRP-TpU7bY0g0", "nationalPhoneNumber": "(585) 671-5133", "formattedAddress": "1763 Empire Blvd, Webster, NY 14580, USA", "addressComponents": [{"longText": "1763", "shortText": "1763", "types": ["street_number"], "languageCode": "en-US"}, {"longText": "Empire Boulevard", "shortText": "Empire Blvd", "types": ["route"], "languageCode": "en"}, {"longText": "Webster", "shortText": "Webster", "types": ["locality", "political"], "languageCode": "en"}, {"longText": "Penfield", "shortText": "Penfield", "types": ["administrative_area_level_3", "political"], "languageCode": "en"}, {"longText": "Monroe County", "shortText": "Monroe County", "types": ["administrative_area_level_2", "political"], "languageCode": "en"}, {"longText": "New York", "shortText": "NY", "types": ["administrative_area_level_1", "political"], "languageCode": "en"}, {"longText": "United States", "shortText": "US", "types": ["country", "political"], "languageCode": "en"}, {"longText": "14580", "shortText": "14580", "types": ["postal_code"], "languageCode": "en-US"}], "location": {"latitude": 43.1869862, "longitude": -77.5062928}, "rating": 4.4, "googleMapsUri": "https://maps.google.com/?cid=996096745205785663&g_mp=Cilnb29nbGUubWFwcy5wbGFjZXMudjEuUGxhY2VzLlNlYXJjaE5lYXJieRACGAQgAA", "websiteUri": "http://www.royaldynastyrest.com/", "regularOpeningHours": {"openNow": false, "periods": [{"open": {"day": 0, "hour": 16, "minute": 0}, "close": {"day": 0, "hour": 20, "minute": 30}}, {"open": {"day": 2, "hour": 16, "minute": 0}, "close": {"day": 2, "hour": 20, "minute": 30}}, {"open": {"day": 3, "hour": 16, "minute": 0}, "close": {"day": 3, "hour": 20, "minute": 30}}, {"open": {"day": 4, "hour": 16, "minute": 0}, "close": {"day": 4, "hour": 20, "minute": 30}}, {"open": {"day": 5, "hour": 16, "minute": 0}, "close": {"day": 5, "hour": 21, "minute": 0}}, {"open": {"day": 6, "hour": 16, "minute": 0}, "close": {"day": 6, "hour": 21, "minute": 0}}], "weekdayDescriptions": ["Monday: Closed", "Tuesday: 4:00\u2009\u2013\u20098:30\u202fPM", "Wednesday: 4:00\u2009\u2013\u20098:30\u202fPM", "Thursday: 4:00\u2009\u2013\u20098:30\u202fPM", "Friday: 4:00\u2009\u2013\u20099:00\u202fPM", "Saturday: 4:00\u2009\u2013\u20099:00\u202fPM", "Sunday: 4:00\u2009\u2013\u20098:30\u202fPM"], "nextOpenTime": "2026-02-08T21:00:00Z"}, "businessStatus": "OPERATIONAL", "priceLevel": "PRICE_LEVEL_MODERATE", "userRatingCount": 591, "displayName": {"text": "Royal Dynasty", "languageCode": "en"}, "takeout": true, "delivery": false, "dineIn": true}, {"id": "ChIJdRYfZnDJ1okRYzXEZ3j_PMg", "nationalPhoneNumber": "(585) 670-9999", "formattedAddress": "1217 Bay Rd Suite 5, Webster, NY 14580, USA", "addressComponents": [{"longText": "Suite 5", "shortText": "Suite 5", "types": ["subpremise"], "languageCode": "en"}, {"longText": "1217", "shortText": "1217", "types": ["street_number"], "languageCode": "en-US"}, {"longText": "Bay Road", "shortText": "Bay Rd", "types": ["route"], "languageCode": "en"}, {"longText": "Webster", "shortText": "Webster", "types": ["locality", "political"], "languageCode": "en"}, {"longText": "Penfield", "shortText": "Penfield", "types": ["administrative_area_level_3", "political"], "languageCode": "en"}, {"longText": "Monroe County", "shortText": "Monroe County", "types": ["administrative_area_level_2", "political"], "languageCode": "en"}, {"longText": "New York", "shortText": "NY", "types": ["administrative_area_level_1", "political"], "languageCode": "en"}, {"longText": "United States", "shortText": "US", "types": ["country", "political"], "languageCode": "en"}, {"longText": "14580", "shortText": "14580", "types": ["postal_code"], "languageCode": "en-US"}], "location": {"latitude": 43.1919751, "longitude": -77.50678119999999}, "rating": 4.4, "googleMapsUri": "https://maps.google.com/?cid=14428688198790296931&g_mp=Cilnb29nbGUubWFwcy5wbGFjZXMudjEuUGxhY2VzLlNlYXJjaE5lYXJieRACGAQgAA", "regularOpeningHours": {"openNow": true, "periods": [{"open": {"day": 0, "hour": 12, "minute": 0}, "close": {"day": 0, "hour": 21, "minute": 30}}, {"open": {"day": 2, "hour": 11, "minute": 0}, "close": {"day": 2, "hour": 21, "minute": 30}}, {"open": {"day": 3, "hour": 11, "minute": 0}, "close": {"day": 3, "hour": 21, "minute": 30}}, {"open": {"day": 4, "hour": 11, "minute": 0}, "close": {"day": 4, "hour": 21, "minute": 30}}, {"open": {"day": 5, "hour": 11, "minute": 0}, "close": {"day": 5, "hour": 22, "minute": 30}}, {"open": {"day": 6, "hour": 11, "minute": 0}, "close": {"day": 6, "hour": 22, "minute": 30}}], "weekdayDescriptions": ["Monday: Closed", "Tuesday: 11:00\u202fAM\u2009\u2013\u20099:30\u202fPM", "Wednesday: 11:00\u202fAM\u2009\u2013\u20099:30\u202fPM", "Thursday: 11:00\u202fAM\u2009\u2013\u20099:30\u202fPM", "Friday: 11:00\u202fAM\u2009\u2013\u200910:30\u202fPM", "Saturday: 11:00\u202fAM\u2009\u2013\u200910:30\u202fPM", "Sunday: 12:00\u2009\u2013\u20099:30\u202fPM"], "nextCloseTime": "2026-02-08T03:30:00Z"}, "businessStatus": "OPERATIONAL", "priceLevel": "PRICE_LEVEL_INEXPENSIVE", "userRatingCount": 315, "displayName": {"text": "Spring Garden", "languageCode": "en"}, "takeout": true, "delivery": false, "dineIn": true}]}